{
  "id": 22464,
  "category": "Pics",
  "publishCategory": "Pd",
  "layoutMode": "Published",
  "isCloudProduct": false,
  "title": "純愛女店員趁休假偷偷出外賺外快，在陌生人面前全裸慰慰",
  "description": "<p>在餐廳碰到的女店員</p><p>可愛的臉和制服撐起來的堅挺巨乳</p><p>讓我忍不住偷偷的傳紙條相約</p><p>沒想到居然成功了</p><p>在她休假時帶她來到了訂好的旅館</p><p>這幾天總是時不時的想起她的巨乳</p><p>換上睡衣後，看著她若隱若現的奶頭和胸部</p><p>想理智都難，忍不住的朝她摸去</p><p>她嬌羞的呻吟讓人獸性大發</p><p>現在…讓我好好品嚐妳這甜美的小蘋果❤️</p>",
  "price": 7.99,
  "discountPrice": null,
  "hiddenProductId": 16679,
  "hiddenPrice": 0,
  "diamondPrice": 4000,
  "cover": {
    "thumbnail": "/minify_image/1600/3/1653085718210_56744/2022/05/21/493398be684a3b8ebd0de9c06e06ceaae70151b16c908257249ceb3c3d61eeef.jpg",
    "video": "",
    "type": "photo",
    "ogImage": "/minify_image/1600/3/1653085718210_56744/2022/05/21/493398be684a3b8ebd0de9c06e06ceaae70151b16c908257249ceb3c3d61eeef.jpg",
    "isCompleted": true
  },
  "photoCount": 81,
  "videoLength": null,
  "viewTimes": 3500,
  "favoriteTimes": 12,
  "publishStart": 1653138000000,
  "buyButtonType": "notLogin",
  "bulkButtonType": "hide",
  "tag": [
    {
      "parentTagId": null,
      "color": "#0752BC",
      "nameI18nKey": "tag.naked",
      "id": 118,
      "type": "Boundary"
    },
    {
      "parentTagId": "59",
      "color": "#bebebe",
      "nameI18nKey": "tag.lingerie",
      "id": 65,
      "type": "Genre"
    },
    {
      "parentTagId": "127",
      "color": "#e84989",
      "nameI18nKey": "tag.hiddenVersion",
      "id": 128,
      "type": "Genre"
    }
  ],
  "author": {
    "avatarUrl": "/rescale_avatar/1540985172686_56744/2018/10/31/0b17870d63c5fb3101ad50a959d0572c7e465b3fdb31ae3de74b1c9395b86f06_large.jpg",
    "displayName": "GZP",
    "name": "古志傑",
    "id": 56744
  },
  "presenter": null,
  "producer": null,
  "collaborator": null,
  "crewList": [],
  "modelList": [
    {
      "avatarUrl": "/rescale_avatar/1638539222655_198418/2021/12/03/bac798c9361e035d3ad1d6af85b9b019514c67da319b65d19ebbeb61dab42fed_large.jpg",
      "displayName": "小露斑比",
      "name": "小露斑比",
      "id": 198418
    }
  ],
  "recommendVideo": [
    {
      "id": "aXd8G3Xj",
      "category": "Pics",
      "title": "異想親子丼/隱藏版倫理劇/女兒與父親的相遇竟是在!!!/理性與獸性誰能達陣/隱藏版上架三日1.99元/亂O特別企劃",
      "coverImage": "/video_thumbnail/1646314709317_21212/2022/03/03/640/e00f01e78754343dcbe522b29b79a0f984662caf9fe41030e6f7bb2caac8f299.jpg",
      "coverVideo": "/marked_preview_video/1646314709317_21212/2022/03/03/12c3f3249bd782cf9cd5825e5cf2d03459dc209e57258f9fb643bbb13683eb24.mp4",
      "coverPreviewable": true,
      "originalPrice": 9.99,
      "specialPrice": null,
      "favoriteTimes": 64,
      "viewTimes": 9898,
      "publishStart": 1646319600000,
      "photoCount": 101,
      "videoLength": "00:03:28",
      "hiddenVersionPhotoCount": 4,
      "hiddenVersionVideoLength": "00:21:08",
      "model": [
        {
          "id": 198418,
          "name": "小露斑比",
          "displayName": "小露斑比",
          "avatarUrl": "/rescale_avatar/1638539222655_198418/2021/12/03/bac798c9361e035d3ad1d6af85b9b019514c67da319b65d19ebbeb61dab42fed_small.jpg"
        }
      ]
    },
    {
      "id": "zkPdy9kd",
      "category": "Pics",
      "title": "【全裸露點無遮】🔊🔊🔊讓人酥麻の淫蕩叫聲🎧🎧🎧強制高潮の白漿流出!!! 影片長27分!!! 照片只是附屬，影片才是主體!!!",
      "coverImage": "/video_thumbnail/1660563980339_68468/2022/08/15/640/229f37a1846e1d6eaae2fedbe72e44dc668c015a291181c6e7f737fac31547a9.jpg",
      "coverVideo": "/marked_preview_video/1660563980339_68468/2022/08/15/8ef2203e90f46921ae5536cc8873158366d1903a9ef9775dbd334b6be5fcea3d.mp4",
      "coverPreviewable": true,
      "originalPrice": 9.99,
      "specialPrice": null,
      "favoriteTimes": 86,
      "viewTimes": 17396,
      "publishStart": 1660566600000,
      "photoCount": 70,
      "videoLength": "00:27:35",
      "hiddenVersionPhotoCount": 0,
      "hiddenVersionVideoLength": null,
      "model": [
        {
          "id": 198418,
          "name": "小露斑比",
          "displayName": "小露斑比",
          "avatarUrl": "/rescale_avatar/1638539222655_198418/2021/12/03/bac798c9361e035d3ad1d6af85b9b019514c67da319b65d19ebbeb61dab42fed_small.jpg"
        }
      ]
    },
    {
      "id": "z1YxQNXG",
      "category": "Pics",
      "title": "素人誌/絕對妊娠NTR/老婆約炮友被發現!/嗯~老公請等等我正在高潮~/穴射X2口射X1/隱藏版內附完整29分鐘QR Code",
      "coverImage": "/video_thumbnail/1661695237075_21212/2022/08/28/640/47662fd00a6a7ec7e3479c936df1adaa33875a15833523763a57b05ded0f3fc6.jpg",
      "coverVideo": "/marked_preview_video/1661695237075_21212/2022/08/28/e319b5debf4204a160a5113d5fb1fd53368cb59b687cecabd0b0d6de055c9864.mp4",
      "coverPreviewable": true,
      "originalPrice": 12.99,
      "specialPrice": null,
      "favoriteTimes": 68,
      "viewTimes": 6655,
      "publishStart": 1661698800000,
      "photoCount": 134,
      "videoLength": "00:04:07",
      "hiddenVersionPhotoCount": 4,
      "hiddenVersionVideoLength": "00:04:07",
      "model": [
        {
          "id": 198418,
          "name": "小露斑比",
          "displayName": "小露斑比",
          "avatarUrl": "/rescale_avatar/1638539222655_198418/2021/12/03/bac798c9361e035d3ad1d6af85b9b019514c67da319b65d19ebbeb61dab42fed_small.jpg"
        }
      ]
    },
    {
      "id": "31v5bMX0",
      "category": "Pics",
      "title": "【過激愛情動作片】超巨乳秘書斑比背德開會中【隱藏版嬌喘影片】",
      "coverImage": "/minify_image/300/1661705515292_32689/2022/08/29/96a6f1551dd605c3901293370f7caed13cdd0ada6092f83d295886d23db0fd6d.jpg",
      "coverVideo": null,
      "coverPreviewable": false,
      "originalPrice": 10.99,
      "specialPrice": null,
      "favoriteTimes": 23,
      "viewTimes": 5975,
      "publishStart": 1662127200000,
      "photoCount": 99,
      "videoLength": null,
      "hiddenVersionPhotoCount": 31,
      "hiddenVersionVideoLength": "00:09:25",
      "model": [
        {
          "id": 198418,
          "name": "小露斑比",
          "displayName": "小露斑比",
          "avatarUrl": "/rescale_avatar/1638539222655_198418/2021/12/03/bac798c9361e035d3ad1d6af85b9b019514c67da319b65d19ebbeb61dab42fed_small.jpg"
        }
      ]
    },
    {
      "id": "OXDYmP18",
      "category": "Pics",
      "title": "素人誌/DUBLE E CUP/雙重美人乳愛/首次公開呻吟尺度/激情隱藏版三日0元",
      "coverImage": "/video_thumbnail/1643506169473_21212/2022/01/30/640/ad5c2ebbc77e4397f6427e57d3720db5f11bff598d7801c283ad76d0a339d6aa.jpg",
      "coverVideo": "/marked_preview_video/1643506169473_21212/2022/01/30/88a0c533850603fc377991b3a772330fd8592e56a744bfa60baf854fe2635b46.mp4",
      "coverPreviewable": true,
      "originalPrice": 12.99,
      "specialPrice": null,
      "favoriteTimes": 58,
      "viewTimes": 12367,
      "publishStart": 1643508000000,
      "photoCount": 100,
      "videoLength": "00:11:11",
      "hiddenVersionPhotoCount": 9,
      "hiddenVersionVideoLength": "00:12:09",
      "model": [
        {
          "id": 59178,
          "name": "莎莉",
          "displayName": "莎莉",
          "avatarUrl": "/rescale_avatar/1643106276241_59178/2022/01/25/d2a0942f79ed3ad369bfcc153ce9bb0a8320336a375c361def53207a857937be_small.jpg"
        },
        {
          "id": 198418,
          "name": "小露斑比",
          "displayName": "小露斑比",
          "avatarUrl": "/rescale_avatar/1638539222655_198418/2021/12/03/bac798c9361e035d3ad1d6af85b9b019514c67da319b65d19ebbeb61dab42fed_small.jpg"
        }
      ]
    }
  ],
  "recommendModel": [
    {
      "avatarUrl": "/rescale_avatar/1539572545595_1006/2018/10/15/02384fbafee4ad309e831402bd1d5a9ddb94714b507e3c52c4a15254ac3272ce_large.jpg",
      "displayName": "艾青iris",
      "name": "lovebabyiris",
      "id": 54443
    },
    {
      "avatarUrl": "/rescale_avatar/1624944785859_369431/2021/06/29/0a90387dd6029194610f108adab3cd3f265ff3ccbf1f8199dc2fba60986a1f7d_large.jpg",
      "displayName": "貝拉拉",
      "name": "貝拉拉",
      "id": 369431
    },
    {
      "avatarUrl": "/rescale_avatar/1644660508160_409746/2022/02/12/c7b0b15d269f951906f2651f6908e95f7c156faed8aa258ac2d6a4eb3270b970_large.jpg",
      "displayName": "小蠍",
      "name": "Rose5920",
      "id": 409746
    },
    {
      "avatarUrl": "/rescale_avatar/1665127288255_597130/2022/10/07/9a329a7b8d11eec2a9278c16a303436139be117f891191e749efef537f8897cd_large.jpg",
      "displayName": "IGHOT-小七❤️",
      "name": "IGHOT-小七❤️",
      "id": 597130
    },
    {
      "avatarUrl": "/rescale_avatar/1592189057990_214881/2020/06/15/69255937e95a43f6681368e6163bfae2e9705b8d7d44a1aea57119a6cfbe0843_large.jpg",
      "displayName": "涼宮琴音",
      "name": "涼宮琴音",
      "id": 214881
    },
    {
      "avatarUrl": "/rescale_avatar/1629101434315_363801/2021/08/16/75e39dfcbc22f83934fc9260d96344701595a7ebe1acb2eed43b0b5f5f125e25_large.jpg",
      "displayName": "Aaliyah",
      "name": "Aaliyah",
      "id": 363801
    },
    {
      "avatarUrl": "/rescale_avatar/1681484829053_479121/2023/04/14/fef579739f00039dce30169587517fa1a3cbb37f6706132cbe771e98ccb1982a_large.jpeg",
      "displayName": "皊皊",
      "name": "你家的小祖宗-皊皊",
      "id": 479121
    },
    {
      "avatarUrl": "/rescale_avatar/1678713386521_540241/2023/03/13/2cb1a415c042c78634baada3bcda7114fa2f648857479c8fc19d9f18ea72633b_large.jpeg",
      "displayName": "露露咪",
      "name": "露露咪",
      "id": 540241
    }
  ],
  "productMedia": {
    "hiddenProductFree": [],
    "hiddenProductPaid": [
      {
        "id": 1304129,
        "type": "photo",
        "isCover": false,
        "isNoticeCover": false,
        "isPreorderCover": false,
        "isCompleted": true,
        "isPreview": false,
        "previewVideoUri": null,
        "thumbnailUrl": null,
        "contentUrl": null,
        "visionResult": {
          "leftEye": {
            "x": 0,
            "y": 0,
            "z": 0,
            "xPercentage": 0,
            "yPercentage": 0
          },
          "rightEye": {
            "x": 0,
            "y": 0,
            "z": 0,
            "xPercentage": 0,
            "yPercentage": 0
          }
        },
        "width": 1920,
        "height": 1080,
        "length": null
      },
      {
        "id": 1304127,
        "type": "photo",
        "isCover": false,
        "isNoticeCover": false,
        "isPreorderCover": false,
        "isCompleted": true,
        "isPreview": false,
        "previewVideoUri": null,
        "thumbnailUrl": null,
        "contentUrl": null,
        "visionResult": {
          "leftEye": {
            "x": 0,
            "y": 0,
            "z": 0,
            "xPercentage": 0,
            "yPercentage": 0
          },
          "rightEye": {
            "x": 0,
            "y": 0,
            "z": 0,
            "xPercentage": 0,
            "yPercentage": 0
          }
        },
        "width": 1920,
        "height": 1080,
        "length": null
      },
      {
        "id": 1304132,
        "type": "photo",
        "isCover": false,
        "isNoticeCover": false,
        "isPreorderCover": false,
        "isCompleted": true,
        "isPreview": false,
        "previewVideoUri": null,
        "thumbnailUrl": null,
        "contentUrl": null,
        "visionResult": {
          "leftEye": {
            "x": 0,
            "y": 0,
            "z": 0,
            "xPercentage": 0,
            "yPercentage": 0
          },
          "rightEye": {
            "x": 0,
            "y": 0,
            "z": 0,
            "xPercentage": 0,
            "yPercentage": 0
          }
        },
        "width": 1920,
        "height": 1080,
        "length": null
      }
    ],
    "main": [
      {
        "id": 1304208,
        "type": "photo",
        "isCover": false,
        "isNoticeCover": false,
        "isPreorderCover": false,
        "isCompleted": true,
        "isPreview": true,
        "previewVideoUri": null,
        "thumbnailUrl": "/minify_image/300/1653085718210_56744/2022/05/21/3880346a6a4fa4dd0f3ed6408cb010770fbcde6e8b60ffb473c0060f72fbbedb.jpg",
        "contentUrl": "/minify_image/1600/3/1653085718210_56744/2022/05/21/3880346a6a4fa4dd0f3ed6408cb010770fbcde6e8b60ffb473c0060f72fbbedb.jpg",
        "visionResult": {
          "leftEye": {
            "x": 0,
            "y": 0,
            "z": 0,
            "xPercentage": 0,
            "yPercentage": 0
          },
          "rightEye": {
            "x": 0,
            "y": 0,
            "z": 0,
            "xPercentage": 0,
            "yPercentage": 0
          }
        },
        "width": 1920,
        "height": 1080,
        "length": null
      },
      {
        "id": 1304209,
        "type": "photo",
        "isCover": false,
        "isNoticeCover": false,
        "isPreorderCover": false,
        "isCompleted": true,
        "isPreview": true,
        "previewVideoUri": null,
        "thumbnailUrl": "/minify_image/300/1653085718210_56744/2022/05/21/8305683105319b44ecac9b02e2e38c0ebfdb9a7d16602712c7a1e09a582e74ed.jpg",
        "contentUrl": "/minify_image/1600/3/1653085718210_56744/2022/05/21/8305683105319b44ecac9b02e2e38c0ebfdb9a7d16602712c7a1e09a582e74ed.jpg",
        "visionResult": {
          "leftEye": {
            "x": 0,
            "y": 0,
            "z": 0,
            "xPercentage": 0,
            "yPercentage": 0
          },
          "rightEye": {
            "x": 0,
            "y": 0,
            "z": 0,
            "xPercentage": 0,
            "yPercentage": 0
          }
        },
        "width": 1920,
        "height": 1080,
        "length": null
      },
      {
        "id": 1304210,
        "type": "photo",
        "isCover": false,
        "isNoticeCover": false,
        "isPreorderCover": false,
        "isCompleted": true,
        "isPreview": true,
        "previewVideoUri": null,
        "thumbnailUrl": "/minify_image/300/1653085718210_56744/2022/05/21/ed6eb739af63c2396b28b15ea4305eb04b9140d837f326fedf2fbec50b02115d.jpg",
        "contentUrl": "/minify_image/1600/3/1653085718210_56744/2022/05/21/ed6eb739af63c2396b28b15ea4305eb04b9140d837f326fedf2fbec50b02115d.jpg",
        "visionResult": {
          "leftEye": {
            "x": 0,
            "y": 0,
            "z": 0,
            "xPercentage": 0,
            "yPercentage": 0
          },
          "rightEye": {
            "x": 0,
            "y": 0,
            "z": 0,
            "xPercentage": 0,
            "yPercentage": 0
          }
        },
        "width": 1920,
        "height": 1080,
        "length": null
      },
      {
        "id": 1304211,
        "type": "photo",
        "isCover": true,
        "isNoticeCover": false,
        "isPreorderCover": false,
        "isCompleted": true,
        "isPreview": true,
        "previewVideoUri": null,
        "thumbnailUrl": "/minify_image/300/1653085718210_56744/2022/05/21/493398be684a3b8ebd0de9c06e06ceaae70151b16c908257249ceb3c3d61eeef.jpg",
        "contentUrl": "/minify_image/1600/3/1653085718210_56744/2022/05/21/493398be684a3b8ebd0de9c06e06ceaae70151b16c908257249ceb3c3d61eeef.jpg",
        "visionResult": {
          "leftEye": {
            "x": 0,
            "y": 0,
            "z": 0,
            "xPercentage": 0,
            "yPercentage": 0
          },
          "rightEye": {
            "x": 0,
            "y": 0,
            "z": 0,
            "xPercentage": 0,
            "yPercentage": 0
          }
        },
        "width": 1920,
        "height": 1080,
        "length": null
      },
      {
        "id": 1304183,
        "type": "photo",
        "isCover": false,
        "isNoticeCover": false,
        "isPreorderCover": false,
        "isCompleted": true,
        "isPreview": false,
        "previewVideoUri": null,
        "thumbnailUrl": null,
        "contentUrl": null,
        "visionResult": {
          "leftEye": {
            "x": 0,
            "y": 0,
            "z": 0,
            "xPercentage": 0,
            "yPercentage": 0
          },
          "rightEye": {
            "x": 0,
            "y": 0,
            "z": 0,
            "xPercentage": 0,
            "yPercentage": 0
          }
        },
        "width": 1920,
        "height": 1080,
        "length": null
      },
      {
        "id": 1304144,
        "type": "photo",
        "isCover": false,
        "isNoticeCover": false,
        "isPreorderCover": false,
        "isCompleted": true,
        "isPreview": false,
        "previewVideoUri": null,
        "thumbnailUrl": null,
        "contentUrl": null,
        "visionResult": {
          "leftEye": {
            "x": 0,
            "y": 0,
            "z": 0,
            "xPercentage": 0,
            "yPercentage": 0
          },
          "rightEye": {
            "x": 0,
            "y": 0,
            "z": 0,
            "xPercentage": 0,
            "yPercentage": 0
          }
        },
        "width": 1920,
        "height": 1080,
        "length": null
      },
      {
        "id": 1304173,
        "type": "photo",
        "isCover": false,
        "isNoticeCover": false,
        "isPreorderCover": false,
        "isCompleted": true,
        "isPreview": false,
        "previewVideoUri": null,
        "thumbnailUrl": null,
        "contentUrl": null,
        "visionResult": {
          "leftEye": {
            "x": 0,
            "y": 0,
            "z": 0,
            "xPercentage": 0,
            "yPercentage": 0
          },
          "rightEye": {
            "x": 0,
            "y": 0,
            "z": 0,
            "xPercentage": 0,
            "yPercentage": 0
          }
        },
        "width": 1920,
        "height": 1080,
        "length": null
      },
      {
        "id": 1304181,
        "type": "photo",
        "isCover": false,
        "isNoticeCover": false,
        "isPreorderCover": false,
        "isCompleted": true,
        "isPreview": false,
        "previewVideoUri": null,
        "thumbnailUrl": null,
        "contentUrl": null,
        "visionResult": {
          "leftEye": {
            "x": 0,
            "y": 0,
            "z": 0,
            "xPercentage": 0,
            "yPercentage": 0
          },
          "rightEye": {
            "x": 0,
            "y": 0,
            "z": 0,
            "xPercentage": 0,
            "yPercentage": 0
          }
        },
        "width": 1920,
        "height": 1080,
        "length": null
      },
      {
        "id": 1304159,
        "type": "photo",
        "isCover": false,
        "isNoticeCover": false,
        "isPreorderCover": false,
        "isCompleted": true,
        "isPreview": false,
        "previewVideoUri": null,
        "thumbnailUrl": null,
        "contentUrl": null,
        "visionResult": {
          "leftEye": {
            "x": 0,
            "y": 0,
            "z": 0,
            "xPercentage": 0,
            "yPercentage": 0
          },
          "rightEye": {
            "x": 0,
            "y": 0,
            "z": 0,
            "xPercentage": 0,
            "yPercentage": 0
          }
        },
        "width": 1920,
        "height": 1080,
        "length": null
      },
      {
        "id": 1304184,
        "type": "photo",
        "isCover": false,
        "isNoticeCover": false,
        "isPreorderCover": false,
        "isCompleted": true,
        "isPreview": false,
        "previewVideoUri": null,
        "thumbnailUrl": null,
        "contentUrl": null,
        "visionResult": {
          "leftEye": {
            "x": 0,
            "y": 0,
            "z": 0,
            "xPercentage": 0,
            "yPercentage": 0
          },
          "rightEye": {
            "x": 0,
            "y": 0,
            "z": 0,
            "xPercentage": 0,
            "yPercentage": 0
          }
        },
        "width": 1920,
        "height": 1080,
        "length": null
      },
      {
        "id": 1304166,
        "type": "photo",
        "isCover": false,
        "isNoticeCover": false,
        "isPreorderCover": false,
        "isCompleted": true,
        "isPreview": false,
        "previewVideoUri": null,
        "thumbnailUrl": null,
        "contentUrl": null,
        "visionResult": {
          "leftEye": {
            "x": 0,
            "y": 0,
            "z": 0,
            "xPercentage": 0,
            "yPercentage": 0
          },
          "rightEye": {
            "x": 0,
            "y": 0,
            "z": 0,
            "xPercentage": 0,
            "yPercentage": 0
          }
        },
        "width": 1920,
        "height": 1080,
        "length": null
      },
      {
        "id": 1304187,
        "type": "photo",
        "isCover": false,
        "isNoticeCover": false,
        "isPreorderCover": false,
        "isCompleted": true,
        "isPreview": false,
        "previewVideoUri": null,
        "thumbnailUrl": null,
        "contentUrl": null,
        "visionResult": {
          "leftEye": {
            "x": 0,
            "y": 0,
            "z": 0,
            "xPercentage": 0,
            "yPercentage": 0
          },
          "rightEye": {
            "x": 0,
            "y": 0,
            "z": 0,
            "xPercentage": 0,
            "yPercentage": 0
          }
        },
        "width": 1920,
        "height": 1080,
        "length": null
      },
      {
        "id": 1304168,
        "type": "photo",
        "isCover": false,
        "isNoticeCover": false,
        "isPreorderCover": false,
        "isCompleted": true,
        "isPreview": false,
        "previewVideoUri": null,
        "thumbnailUrl": null,
        "contentUrl": null,
        "visionResult": {
          "leftEye": {
            "x": 0,
            "y": 0,
            "z": 0,
            "xPercentage": 0,
            "yPercentage": 0
          },
          "rightEye": {
            "x": 0,
            "y": 0,
            "z": 0,
            "xPercentage": 0,
            "yPercentage": 0
          }
        },
        "width": 1920,
        "height": 1080,
        "length": null
      },
      {
        "id": 1304172,
        "type": "photo",
        "isCover": false,
        "isNoticeCover": false,
        "isPreorderCover": false,
        "isCompleted": true,
        "isPreview": false,
        "previewVideoUri": null,
        "thumbnailUrl": null,
        "contentUrl": null,
        "visionResult": {
          "leftEye": {
            "x": 0,
            "y": 0,
            "z": 0,
            "xPercentage": 0,
            "yPercentage": 0
          },
          "rightEye": {
            "x": 0,
            "y": 0,
            "z": 0,
            "xPercentage": 0,
            "yPercentage": 0
          }
        },
        "width": 1920,
        "height": 1080,
        "length": null
      },
      {
        "id": 1304138,
        "type": "photo",
        "isCover": false,
        "isNoticeCover": false,
        "isPreorderCover": false,
        "isCompleted": true,
        "isPreview": false,
        "previewVideoUri": null,
        "thumbnailUrl": null,
        "contentUrl": null,
        "visionResult": {
          "leftEye": {
            "x": 0,
            "y": 0,
            "z": 0,
            "xPercentage": 0,
            "yPercentage": 0
          },
          "rightEye": {
            "x": 0,
            "y": 0,
            "z": 0,
            "xPercentage": 0,
            "yPercentage": 0
          }
        },
        "width": 1920,
        "height": 1080,
        "length": null
      },
      {
        "id": 1304174,
        "type": "photo",
        "isCover": false,
        "isNoticeCover": false,
        "isPreorderCover": false,
        "isCompleted": true,
        "isPreview": false,
        "previewVideoUri": null,
        "thumbnailUrl": null,
        "contentUrl": null,
        "visionResult": {
          "leftEye": {
            "x": 0,
            "y": 0,
            "z": 0,
            "xPercentage": 0,
            "yPercentage": 0
          },
          "rightEye": {
            "x": 0,
            "y": 0,
            "z": 0,
            "xPercentage": 0,
            "yPercentage": 0
          }
        },
        "width": 1920,
        "height": 1080,
        "length": null
      },
      {
        "id": 1304134,
        "type": "photo",
        "isCover": false,
        "isNoticeCover": false,
        "isPreorderCover": false,
        "isCompleted": true,
        "isPreview": false,
        "previewVideoUri": null,
        "thumbnailUrl": null,
        "contentUrl": null,
        "visionResult": {
          "leftEye": {
            "x": 0,
            "y": 0,
            "z": 0,
            "xPercentage": 0,
            "yPercentage": 0
          },
          "rightEye": {
            "x": 0,
            "y": 0,
            "z": 0,
            "xPercentage": 0,
            "yPercentage": 0
          }
        },
        "width": 1920,
        "height": 1080,
        "length": null
      },
      {
        "id": 1304136,
        "type": "photo",
        "isCover": false,
        "isNoticeCover": false,
        "isPreorderCover": false,
        "isCompleted": true,
        "isPreview": false,
        "previewVideoUri": null,
        "thumbnailUrl": null,
        "contentUrl": null,
        "visionResult": {
          "leftEye": {
            "x": 0,
            "y": 0,
            "z": 0,
            "xPercentage": 0,
            "yPercentage": 0
          },
          "rightEye": {
            "x": 0,
            "y": 0,
            "z": 0,
            "xPercentage": 0,
            "yPercentage": 0
          }
        },
        "width": 1920,
        "height": 1080,
        "length": null
      },
      {
        "id": 1304177,
        "type": "photo",
        "isCover": false,
        "isNoticeCover": false,
        "isPreorderCover": false,
        "isCompleted": true,
        "isPreview": false,
        "previewVideoUri": null,
        "thumbnailUrl": null,
        "contentUrl": null,
        "visionResult": {
          "leftEye": {
            "x": 0,
            "y": 0,
            "z": 0,
            "xPercentage": 0,
            "yPercentage": 0
          },
          "rightEye": {
            "x": 0,
            "y": 0,
            "z": 0,
            "xPercentage": 0,
            "yPercentage": 0
          }
        },
        "width": 1920,
        "height": 1080,
        "length": null
      },
      {
        "id": 1304148,
        "type": "photo",
        "isCover": false,
        "isNoticeCover": false,
        "isPreorderCover": false,
        "isCompleted": true,
        "isPreview": false,
        "previewVideoUri": null,
        "thumbnailUrl": null,
        "contentUrl": null,
        "visionResult": {
          "leftEye": {
            "x": 0,
            "y": 0,
            "z": 0,
            "xPercentage": 0,
            "yPercentage": 0
          },
          "rightEye": {
            "x": 0,
            "y": 0,
            "z": 0,
            "xPercentage": 0,
            "yPercentage": 0
          }
        },
        "width": 1920,
        "height": 1080,
        "length": null
      },
      {
        "id": 1304156,
        "type": "photo",
        "isCover": false,
        "isNoticeCover": false,
        "isPreorderCover": false,
        "isCompleted": true,
        "isPreview": false,
        "previewVideoUri": null,
        "thumbnailUrl": null,
        "contentUrl": null,
        "visionResult": {
          "leftEye": {
            "x": 0,
            "y": 0,
            "z": 0,
            "xPercentage": 0,
            "yPercentage": 0
          },
          "rightEye": {
            "x": 0,
            "y": 0,
            "z": 0,
            "xPercentage": 0,
            "yPercentage": 0
          }
        },
        "width": 1920,
        "height": 1080,
        "length": null
      },
      {
        "id": 1304161,
        "type": "photo",
        "isCover": false,
        "isNoticeCover": false,
        "isPreorderCover": false,
        "isCompleted": true,
        "isPreview": false,
        "previewVideoUri": null,
        "thumbnailUrl": null,
        "contentUrl": null,
        "visionResult": {
          "leftEye": {
            "x": 0,
            "y": 0,
            "z": 0,
            "xPercentage": 0,
            "yPercentage": 0
          },
          "rightEye": {
            "x": 0,
            "y": 0,
            "z": 0,
            "xPercentage": 0,
            "yPercentage": 0
          }
        },
        "width": 1920,
        "height": 1080,
        "length": null
      },
      {
        "id": 1304142,
        "type": "photo",
        "isCover": false,
        "isNoticeCover": false,
        "isPreorderCover": false,
        "isCompleted": true,
        "isPreview": false,
        "previewVideoUri": null,
        "thumbnailUrl": null,
        "contentUrl": null,
        "visionResult": {
          "leftEye": {
            "x": 0,
            "y": 0,
            "z": 0,
            "xPercentage": 0,
            "yPercentage": 0
          },
          "rightEye": {
            "x": 0,
            "y": 0,
            "z": 0,
            "xPercentage": 0,
            "yPercentage": 0
          }
        },
        "width": 1920,
        "height": 1080,
        "length": null
      },
      {
        "id": 1304151,
        "type": "photo",
        "isCover": false,
        "isNoticeCover": false,
        "isPreorderCover": false,
        "isCompleted": true,
        "isPreview": false,
        "previewVideoUri": null,
        "thumbnailUrl": null,
        "contentUrl": null,
        "visionResult": {
          "leftEye": {
            "x": 0,
            "y": 0,
            "z": 0,
            "xPercentage": 0,
            "yPercentage": 0
          },
          "rightEye": {
            "x": 0,
            "y": 0,
            "z": 0,
            "xPercentage": 0,
            "yPercentage": 0
          }
        },
        "width": 1920,
        "height": 1080,
        "length": null
      },
      {
        "id": 1304149,
        "type": "photo",
        "isCover": false,
        "isNoticeCover": false,
        "isPreorderCover": false,
        "isCompleted": true,
        "isPreview": false,
        "previewVideoUri": null,
        "thumbnailUrl": null,
        "contentUrl": null,
        "visionResult": {
          "leftEye": {
            "x": 0,
            "y": 0,
            "z": 0,
            "xPercentage": 0,
            "yPercentage": 0
          },
          "rightEye": {
            "x": 0,
            "y": 0,
            "z": 0,
            "xPercentage": 0,
            "yPercentage": 0
          }
        },
        "width": 1920,
        "height": 1080,
        "length": null
      },
      {
        "id": 1304141,
        "type": "photo",
        "isCover": false,
        "isNoticeCover": false,
        "isPreorderCover": false,
        "isCompleted": true,
        "isPreview": false,
        "previewVideoUri": null,
        "thumbnailUrl": null,
        "contentUrl": null,
        "visionResult": {
          "leftEye": {
            "x": 0,
            "y": 0,
            "z": 0,
            "xPercentage": 0,
            "yPercentage": 0
          },
          "rightEye": {
            "x": 0,
            "y": 0,
            "z": 0,
            "xPercentage": 0,
            "yPercentage": 0
          }
        },
        "width": 1920,
        "height": 1080,
        "length": null
      },
      {
        "id": 1304158,
        "type": "photo",
        "isCover": false,
        "isNoticeCover": false,
        "isPreorderCover": false,
        "isCompleted": true,
        "isPreview": false,
        "previewVideoUri": null,
        "thumbnailUrl": null,
        "contentUrl": null,
        "visionResult": {
          "leftEye": {
            "x": 0,
            "y": 0,
            "z": 0,
            "xPercentage": 0,
            "yPercentage": 0
          },
          "rightEye": {
            "x": 0,
            "y": 0,
            "z": 0,
            "xPercentage": 0,
            "yPercentage": 0
          }
        },
        "width": 1920,
        "height": 1080,
        "length": null
      },
      {
        "id": 1304179,
        "type": "photo",
        "isCover": false,
        "isNoticeCover": false,
        "isPreorderCover": false,
        "isCompleted": true,
        "isPreview": false,
        "previewVideoUri": null,
        "thumbnailUrl": null,
        "contentUrl": null,
        "visionResult": {
          "leftEye": {
            "x": 0,
            "y": 0,
            "z": 0,
            "xPercentage": 0,
            "yPercentage": 0
          },
          "rightEye": {
            "x": 0,
            "y": 0,
            "z": 0,
            "xPercentage": 0,
            "yPercentage": 0
          }
        },
        "width": 1920,
        "height": 1080,
        "length": null
      },
      {
        "id": 1304176,
        "type": "photo",
        "isCover": false,
        "isNoticeCover": false,
        "isPreorderCover": false,
        "isCompleted": true,
        "isPreview": false,
        "previewVideoUri": null,
        "thumbnailUrl": null,
        "contentUrl": null,
        "visionResult": {
          "leftEye": {
            "x": 0,
            "y": 0,
            "z": 0,
            "xPercentage": 0,
            "yPercentage": 0
          },
          "rightEye": {
            "x": 0,
            "y": 0,
            "z": 0,
            "xPercentage": 0,
            "yPercentage": 0
          }
        },
        "width": 1920,
        "height": 1080,
        "length": null
      },
      {
        "id": 1304162,
        "type": "photo",
        "isCover": false,
        "isNoticeCover": false,
        "isPreorderCover": false,
        "isCompleted": true,
        "isPreview": false,
        "previewVideoUri": null,
        "thumbnailUrl": null,
        "contentUrl": null,
        "visionResult": {
          "leftEye": {
            "x": 0,
            "y": 0,
            "z": 0,
            "xPercentage": 0,
            "yPercentage": 0
          },
          "rightEye": {
            "x": 0,
            "y": 0,
            "z": 0,
            "xPercentage": 0,
            "yPercentage": 0
          }
        },
        "width": 1920,
        "height": 1080,
        "length": null
      },
      {
        "id": 1304160,
        "type": "photo",
        "isCover": false,
        "isNoticeCover": false,
        "isPreorderCover": false,
        "isCompleted": true,
        "isPreview": false,
        "previewVideoUri": null,
        "thumbnailUrl": null,
        "contentUrl": null,
        "visionResult": {
          "leftEye": {
            "x": 0,
            "y": 0,
            "z": 0,
            "xPercentage": 0,
            "yPercentage": 0
          },
          "rightEye": {
            "x": 0,
            "y": 0,
            "z": 0,
            "xPercentage": 0,
            "yPercentage": 0
          }
        },
        "width": 1920,
        "height": 1080,
        "length": null
      },
      {
        "id": 1304171,
        "type": "photo",
        "isCover": false,
        "isNoticeCover": false,
        "isPreorderCover": false,
        "isCompleted": true,
        "isPreview": false,
        "previewVideoUri": null,
        "thumbnailUrl": null,
        "contentUrl": null,
        "visionResult": {
          "leftEye": {
            "x": 0,
            "y": 0,
            "z": 0,
            "xPercentage": 0,
            "yPercentage": 0
          },
          "rightEye": {
            "x": 0,
            "y": 0,
            "z": 0,
            "xPercentage": 0,
            "yPercentage": 0
          }
        },
        "width": 1920,
        "height": 1080,
        "length": null
      },
      {
        "id": 1304150,
        "type": "photo",
        "isCover": false,
        "isNoticeCover": false,
        "isPreorderCover": false,
        "isCompleted": true,
        "isPreview": false,
        "previewVideoUri": null,
        "thumbnailUrl": null,
        "contentUrl": null,
        "visionResult": {
          "leftEye": {
            "x": 0,
            "y": 0,
            "z": 0,
            "xPercentage": 0,
            "yPercentage": 0
          },
          "rightEye": {
            "x": 0,
            "y": 0,
            "z": 0,
            "xPercentage": 0,
            "yPercentage": 0
          }
        },
        "width": 1920,
        "height": 1080,
        "length": null
      },
      {
        "id": 1304175,
        "type": "photo",
        "isCover": false,
        "isNoticeCover": false,
        "isPreorderCover": false,
        "isCompleted": true,
        "isPreview": false,
        "previewVideoUri": null,
        "thumbnailUrl": null,
        "contentUrl": null,
        "visionResult": {
          "leftEye": {
            "x": 0,
            "y": 0,
            "z": 0,
            "xPercentage": 0,
            "yPercentage": 0
          },
          "rightEye": {
            "x": 0,
            "y": 0,
            "z": 0,
            "xPercentage": 0,
            "yPercentage": 0
          }
        },
        "width": 1920,
        "height": 1080,
        "length": null
      },
      {
        "id": 1304170,
        "type": "photo",
        "isCover": false,
        "isNoticeCover": false,
        "isPreorderCover": false,
        "isCompleted": true,
        "isPreview": false,
        "previewVideoUri": null,
        "thumbnailUrl": null,
        "contentUrl": null,
        "visionResult": {
          "leftEye": {
            "x": 0,
            "y": 0,
            "z": 0,
            "xPercentage": 0,
            "yPercentage": 0
          },
          "rightEye": {
            "x": 0,
            "y": 0,
            "z": 0,
            "xPercentage": 0,
            "yPercentage": 0
          }
        },
        "width": 1920,
        "height": 1080,
        "length": null
      },
      {
        "id": 1304189,
        "type": "photo",
        "isCover": false,
        "isNoticeCover": false,
        "isPreorderCover": false,
        "isCompleted": true,
        "isPreview": false,
        "previewVideoUri": null,
        "thumbnailUrl": null,
        "contentUrl": null,
        "visionResult": {
          "leftEye": {
            "x": 0,
            "y": 0,
            "z": 0,
            "xPercentage": 0,
            "yPercentage": 0
          },
          "rightEye": {
            "x": 0,
            "y": 0,
            "z": 0,
            "xPercentage": 0,
            "yPercentage": 0
          }
        },
        "width": 1920,
        "height": 1080,
        "length": null
      },
      {
        "id": 1304182,
        "type": "photo",
        "isCover": false,
        "isNoticeCover": false,
        "isPreorderCover": false,
        "isCompleted": true,
        "isPreview": false,
        "previewVideoUri": null,
        "thumbnailUrl": null,
        "contentUrl": null,
        "visionResult": {
          "leftEye": {
            "x": 0,
            "y": 0,
            "z": 0,
            "xPercentage": 0,
            "yPercentage": 0
          },
          "rightEye": {
            "x": 0,
            "y": 0,
            "z": 0,
            "xPercentage": 0,
            "yPercentage": 0
          }
        },
        "width": 1920,
        "height": 1080,
        "length": null
      },
      {
        "id": 1304191,
        "type": "photo",
        "isCover": false,
        "isNoticeCover": false,
        "isPreorderCover": false,
        "isCompleted": true,
        "isPreview": false,
        "previewVideoUri": null,
        "thumbnailUrl": null,
        "contentUrl": null,
        "visionResult": {
          "leftEye": {
            "x": 0,
            "y": 0,
            "z": 0,
            "xPercentage": 0,
            "yPercentage": 0
          },
          "rightEye": {
            "x": 0,
            "y": 0,
            "z": 0,
            "xPercentage": 0,
            "yPercentage": 0
          }
        },
        "width": 1920,
        "height": 1080,
        "length": null
      },
      {
        "id": 1304196,
        "type": "photo",
        "isCover": false,
        "isNoticeCover": false,
        "isPreorderCover": false,
        "isCompleted": true,
        "isPreview": false,
        "previewVideoUri": null,
        "thumbnailUrl": null,
        "contentUrl": null,
        "visionResult": {
          "leftEye": {
            "x": 0,
            "y": 0,
            "z": 0,
            "xPercentage": 0,
            "yPercentage": 0
          },
          "rightEye": {
            "x": 0,
            "y": 0,
            "z": 0,
            "xPercentage": 0,
            "yPercentage": 0
          }
        },
        "width": 1920,
        "height": 1080,
        "length": null
      },
      {
        "id": 1304157,
        "type": "photo",
        "isCover": false,
        "isNoticeCover": false,
        "isPreorderCover": false,
        "isCompleted": true,
        "isPreview": false,
        "previewVideoUri": null,
        "thumbnailUrl": null,
        "contentUrl": null,
        "visionResult": {
          "leftEye": {
            "x": 0,
            "y": 0,
            "z": 0,
            "xPercentage": 0,
            "yPercentage": 0
          },
          "rightEye": {
            "x": 0,
            "y": 0,
            "z": 0,
            "xPercentage": 0,
            "yPercentage": 0
          }
        },
        "width": 1920,
        "height": 1080,
        "length": null
      },
      {
        "id": 1304180,
        "type": "photo",
        "isCover": false,
        "isNoticeCover": false,
        "isPreorderCover": false,
        "isCompleted": true,
        "isPreview": false,
        "previewVideoUri": null,
        "thumbnailUrl": null,
        "contentUrl": null,
        "visionResult": {
          "leftEye": {
            "x": 0,
            "y": 0,
            "z": 0,
            "xPercentage": 0,
            "yPercentage": 0
          },
          "rightEye": {
            "x": 0,
            "y": 0,
            "z": 0,
            "xPercentage": 0,
            "yPercentage": 0
          }
        },
        "width": 1920,
        "height": 1080,
        "length": null
      },
      {
        "id": 1304169,
        "type": "photo",
        "isCover": false,
        "isNoticeCover": false,
        "isPreorderCover": false,
        "isCompleted": true,
        "isPreview": false,
        "previewVideoUri": null,
        "thumbnailUrl": null,
        "contentUrl": null,
        "visionResult": {
          "leftEye": {
            "x": 0,
            "y": 0,
            "z": 0,
            "xPercentage": 0,
            "yPercentage": 0
          },
          "rightEye": {
            "x": 0,
            "y": 0,
            "z": 0,
            "xPercentage": 0,
            "yPercentage": 0
          }
        },
        "width": 1920,
        "height": 1080,
        "length": null
      },
      {
        "id": 1304155,
        "type": "photo",
        "isCover": false,
        "isNoticeCover": false,
        "isPreorderCover": false,
        "isCompleted": true,
        "isPreview": false,
        "previewVideoUri": null,
        "thumbnailUrl": null,
        "contentUrl": null,
        "visionResult": {
          "leftEye": {
            "x": 0,
            "y": 0,
            "z": 0,
            "xPercentage": 0,
            "yPercentage": 0
          },
          "rightEye": {
            "x": 0,
            "y": 0,
            "z": 0,
            "xPercentage": 0,
            "yPercentage": 0
          }
        },
        "width": 1920,
        "height": 1080,
        "length": null
      },
      {
        "id": 1304140,
        "type": "photo",
        "isCover": false,
        "isNoticeCover": false,
        "isPreorderCover": false,
        "isCompleted": true,
        "isPreview": false,
        "previewVideoUri": null,
        "thumbnailUrl": null,
        "contentUrl": null,
        "visionResult": {
          "leftEye": {
            "x": 0,
            "y": 0,
            "z": 0,
            "xPercentage": 0,
            "yPercentage": 0
          },
          "rightEye": {
            "x": 0,
            "y": 0,
            "z": 0,
            "xPercentage": 0,
            "yPercentage": 0
          }
        },
        "width": 1920,
        "height": 1080,
        "length": null
      },
      {
        "id": 1304139,
        "type": "photo",
        "isCover": false,
        "isNoticeCover": false,
        "isPreorderCover": false,
        "isCompleted": true,
        "isPreview": false,
        "previewVideoUri": null,
        "thumbnailUrl": null,
        "contentUrl": null,
        "visionResult": {
          "leftEye": {
            "x": 0,
            "y": 0,
            "z": 0,
            "xPercentage": 0,
            "yPercentage": 0
          },
          "rightEye": {
            "x": 0,
            "y": 0,
            "z": 0,
            "xPercentage": 0,
            "yPercentage": 0
          }
        },
        "width": 1920,
        "height": 1080,
        "length": null
      },
      {
        "id": 1304128,
        "type": "photo",
        "isCover": false,
        "isNoticeCover": false,
        "isPreorderCover": false,
        "isCompleted": true,
        "isPreview": false,
        "previewVideoUri": null,
        "thumbnailUrl": null,
        "contentUrl": null,
        "visionResult": {
          "leftEye": {
            "x": 0,
            "y": 0,
            "z": 0,
            "xPercentage": 0,
            "yPercentage": 0
          },
          "rightEye": {
            "x": 0,
            "y": 0,
            "z": 0,
            "xPercentage": 0,
            "yPercentage": 0
          }
        },
        "width": 1920,
        "height": 1080,
        "length": null
      },
      {
        "id": 1304146,
        "type": "photo",
        "isCover": false,
        "isNoticeCover": false,
        "isPreorderCover": false,
        "isCompleted": true,
        "isPreview": false,
        "previewVideoUri": null,
        "thumbnailUrl": null,
        "contentUrl": null,
        "visionResult": {
          "leftEye": {
            "x": 0,
            "y": 0,
            "z": 0,
            "xPercentage": 0,
            "yPercentage": 0
          },
          "rightEye": {
            "x": 0,
            "y": 0,
            "z": 0,
            "xPercentage": 0,
            "yPercentage": 0
          }
        },
        "width": 1920,
        "height": 1080,
        "length": null
      },
      {
        "id": 1304164,
        "type": "photo",
        "isCover": false,
        "isNoticeCover": false,
        "isPreorderCover": false,
        "isCompleted": true,
        "isPreview": false,
        "previewVideoUri": null,
        "thumbnailUrl": null,
        "contentUrl": null,
        "visionResult": {
          "leftEye": {
            "x": 0,
            "y": 0,
            "z": 0,
            "xPercentage": 0,
            "yPercentage": 0
          },
          "rightEye": {
            "x": 0,
            "y": 0,
            "z": 0,
            "xPercentage": 0,
            "yPercentage": 0
          }
        },
        "width": 1920,
        "height": 1080,
        "length": null
      },
      {
        "id": 1304163,
        "type": "photo",
        "isCover": false,
        "isNoticeCover": false,
        "isPreorderCover": false,
        "isCompleted": true,
        "isPreview": false,
        "previewVideoUri": null,
        "thumbnailUrl": null,
        "contentUrl": null,
        "visionResult": {
          "leftEye": {
            "x": 0,
            "y": 0,
            "z": 0,
            "xPercentage": 0,
            "yPercentage": 0
          },
          "rightEye": {
            "x": 0,
            "y": 0,
            "z": 0,
            "xPercentage": 0,
            "yPercentage": 0
          }
        },
        "width": 1920,
        "height": 1080,
        "length": null
      },
      {
        "id": 1304152,
        "type": "photo",
        "isCover": false,
        "isNoticeCover": false,
        "isPreorderCover": false,
        "isCompleted": true,
        "isPreview": false,
        "previewVideoUri": null,
        "thumbnailUrl": null,
        "contentUrl": null,
        "visionResult": {
          "leftEye": {
            "x": 0,
            "y": 0,
            "z": 0,
            "xPercentage": 0,
            "yPercentage": 0
          },
          "rightEye": {
            "x": 0,
            "y": 0,
            "z": 0,
            "xPercentage": 0,
            "yPercentage": 0
          }
        },
        "width": 1920,
        "height": 1080,
        "length": null
      },
      {
        "id": 1304154,
        "type": "photo",
        "isCover": false,
        "isNoticeCover": false,
        "isPreorderCover": false,
        "isCompleted": true,
        "isPreview": false,
        "previewVideoUri": null,
        "thumbnailUrl": null,
        "contentUrl": null,
        "visionResult": {
          "leftEye": {
            "x": 0,
            "y": 0,
            "z": 0,
            "xPercentage": 0,
            "yPercentage": 0
          },
          "rightEye": {
            "x": 0,
            "y": 0,
            "z": 0,
            "xPercentage": 0,
            "yPercentage": 0
          }
        },
        "width": 1920,
        "height": 1080,
        "length": null
      },
      {
        "id": 1304153,
        "type": "photo",
        "isCover": false,
        "isNoticeCover": false,
        "isPreorderCover": false,
        "isCompleted": true,
        "isPreview": false,
        "previewVideoUri": null,
        "thumbnailUrl": null,
        "contentUrl": null,
        "visionResult": {
          "leftEye": {
            "x": 0,
            "y": 0,
            "z": 0,
            "xPercentage": 0,
            "yPercentage": 0
          },
          "rightEye": {
            "x": 0,
            "y": 0,
            "z": 0,
            "xPercentage": 0,
            "yPercentage": 0
          }
        },
        "width": 1920,
        "height": 1080,
        "length": null
      },
      {
        "id": 1304143,
        "type": "photo",
        "isCover": false,
        "isNoticeCover": false,
        "isPreorderCover": false,
        "isCompleted": true,
        "isPreview": false,
        "previewVideoUri": null,
        "thumbnailUrl": null,
        "contentUrl": null,
        "visionResult": {
          "leftEye": {
            "x": 0,
            "y": 0,
            "z": 0,
            "xPercentage": 0,
            "yPercentage": 0
          },
          "rightEye": {
            "x": 0,
            "y": 0,
            "z": 0,
            "xPercentage": 0,
            "yPercentage": 0
          }
        },
        "width": 1920,
        "height": 1080,
        "length": null
      },
      {
        "id": 1304131,
        "type": "photo",
        "isCover": false,
        "isNoticeCover": false,
        "isPreorderCover": false,
        "isCompleted": true,
        "isPreview": false,
        "previewVideoUri": null,
        "thumbnailUrl": null,
        "contentUrl": null,
        "visionResult": {
          "leftEye": {
            "x": 0,
            "y": 0,
            "z": 0,
            "xPercentage": 0,
            "yPercentage": 0
          },
          "rightEye": {
            "x": 0,
            "y": 0,
            "z": 0,
            "xPercentage": 0,
            "yPercentage": 0
          }
        },
        "width": 1920,
        "height": 1080,
        "length": null
      },
      {
        "id": 1304145,
        "type": "photo",
        "isCover": false,
        "isNoticeCover": false,
        "isPreorderCover": false,
        "isCompleted": true,
        "isPreview": false,
        "previewVideoUri": null,
        "thumbnailUrl": null,
        "contentUrl": null,
        "visionResult": {
          "leftEye": {
            "x": 0,
            "y": 0,
            "z": 0,
            "xPercentage": 0,
            "yPercentage": 0
          },
          "rightEye": {
            "x": 0,
            "y": 0,
            "z": 0,
            "xPercentage": 0,
            "yPercentage": 0
          }
        },
        "width": 1920,
        "height": 1080,
        "length": null
      },
      {
        "id": 1304130,
        "type": "photo",
        "isCover": false,
        "isNoticeCover": false,
        "isPreorderCover": false,
        "isCompleted": true,
        "isPreview": false,
        "previewVideoUri": null,
        "thumbnailUrl": null,
        "contentUrl": null,
        "visionResult": {
          "leftEye": {
            "x": 0,
            "y": 0,
            "z": 0,
            "xPercentage": 0,
            "yPercentage": 0
          },
          "rightEye": {
            "x": 0,
            "y": 0,
            "z": 0,
            "xPercentage": 0,
            "yPercentage": 0
          }
        },
        "width": 1920,
        "height": 1080,
        "length": null
      },
      {
        "id": 1304133,
        "type": "photo",
        "isCover": false,
        "isNoticeCover": false,
        "isPreorderCover": false,
        "isCompleted": true,
        "isPreview": false,
        "previewVideoUri": null,
        "thumbnailUrl": null,
        "contentUrl": null,
        "visionResult": {
          "leftEye": {
            "x": 0,
            "y": 0,
            "z": 0,
            "xPercentage": 0,
            "yPercentage": 0
          },
          "rightEye": {
            "x": 0,
            "y": 0,
            "z": 0,
            "xPercentage": 0,
            "yPercentage": 0
          }
        },
        "width": 1920,
        "height": 1080,
        "length": null
      },
      {
        "id": 1304135,
        "type": "photo",
        "isCover": false,
        "isNoticeCover": false,
        "isPreorderCover": false,
        "isCompleted": true,
        "isPreview": false,
        "previewVideoUri": null,
        "thumbnailUrl": null,
        "contentUrl": null,
        "visionResult": {
          "leftEye": {
            "x": 0,
            "y": 0,
            "z": 0,
            "xPercentage": 0,
            "yPercentage": 0
          },
          "rightEye": {
            "x": 0,
            "y": 0,
            "z": 0,
            "xPercentage": 0,
            "yPercentage": 0
          }
        },
        "width": 1920,
        "height": 1080,
        "length": null
      },
      {
        "id": 1304137,
        "type": "photo",
        "isCover": false,
        "isNoticeCover": false,
        "isPreorderCover": false,
        "isCompleted": true,
        "isPreview": false,
        "previewVideoUri": null,
        "thumbnailUrl": null,
        "contentUrl": null,
        "visionResult": {
          "leftEye": {
            "x": 0,
            "y": 0,
            "z": 0,
            "xPercentage": 0,
            "yPercentage": 0
          },
          "rightEye": {
            "x": 0,
            "y": 0,
            "z": 0,
            "xPercentage": 0,
            "yPercentage": 0
          }
        },
        "width": 1920,
        "height": 1080,
        "length": null
      },
      {
        "id": 1304165,
        "type": "photo",
        "isCover": false,
        "isNoticeCover": false,
        "isPreorderCover": false,
        "isCompleted": true,
        "isPreview": false,
        "previewVideoUri": null,
        "thumbnailUrl": null,
        "contentUrl": null,
        "visionResult": {
          "leftEye": {
            "x": 0,
            "y": 0,
            "z": 0,
            "xPercentage": 0,
            "yPercentage": 0
          },
          "rightEye": {
            "x": 0,
            "y": 0,
            "z": 0,
            "xPercentage": 0,
            "yPercentage": 0
          }
        },
        "width": 1920,
        "height": 1080,
        "length": null
      },
      {
        "id": 1304167,
        "type": "photo",
        "isCover": false,
        "isNoticeCover": false,
        "isPreorderCover": false,
        "isCompleted": true,
        "isPreview": false,
        "previewVideoUri": null,
        "thumbnailUrl": null,
        "contentUrl": null,
        "visionResult": {
          "leftEye": {
            "x": 0,
            "y": 0,
            "z": 0,
            "xPercentage": 0,
            "yPercentage": 0
          },
          "rightEye": {
            "x": 0,
            "y": 0,
            "z": 0,
            "xPercentage": 0,
            "yPercentage": 0
          }
        },
        "width": 1920,
        "height": 1080,
        "length": null
      },
      {
        "id": 1304178,
        "type": "photo",
        "isCover": false,
        "isNoticeCover": false,
        "isPreorderCover": false,
        "isCompleted": true,
        "isPreview": false,
        "previewVideoUri": null,
        "thumbnailUrl": null,
        "contentUrl": null,
        "visionResult": {
          "leftEye": {
            "x": 0,
            "y": 0,
            "z": 0,
            "xPercentage": 0,
            "yPercentage": 0
          },
          "rightEye": {
            "x": 0,
            "y": 0,
            "z": 0,
            "xPercentage": 0,
            "yPercentage": 0
          }
        },
        "width": 1920,
        "height": 1080,
        "length": null
      },
      {
        "id": 1304185,
        "type": "photo",
        "isCover": false,
        "isNoticeCover": false,
        "isPreorderCover": false,
        "isCompleted": true,
        "isPreview": false,
        "previewVideoUri": null,
        "thumbnailUrl": null,
        "contentUrl": null,
        "visionResult": {
          "leftEye": {
            "x": 0,
            "y": 0,
            "z": 0,
            "xPercentage": 0,
            "yPercentage": 0
          },
          "rightEye": {
            "x": 0,
            "y": 0,
            "z": 0,
            "xPercentage": 0,
            "yPercentage": 0
          }
        },
        "width": 1920,
        "height": 1080,
        "length": null
      },
      {
        "id": 1304197,
        "type": "photo",
        "isCover": false,
        "isNoticeCover": false,
        "isPreorderCover": false,
        "isCompleted": true,
        "isPreview": false,
        "previewVideoUri": null,
        "thumbnailUrl": null,
        "contentUrl": null,
        "visionResult": {
          "leftEye": {
            "x": 0,
            "y": 0,
            "z": 0,
            "xPercentage": 0,
            "yPercentage": 0
          },
          "rightEye": {
            "x": 0,
            "y": 0,
            "z": 0,
            "xPercentage": 0,
            "yPercentage": 0
          }
        },
        "width": 1920,
        "height": 1080,
        "length": null
      },
      {
        "id": 1304198,
        "type": "photo",
        "isCover": false,
        "isNoticeCover": false,
        "isPreorderCover": false,
        "isCompleted": true,
        "isPreview": false,
        "previewVideoUri": null,
        "thumbnailUrl": null,
        "contentUrl": null,
        "visionResult": {
          "leftEye": {
            "x": 0,
            "y": 0,
            "z": 0,
            "xPercentage": 0,
            "yPercentage": 0
          },
          "rightEye": {
            "x": 0,
            "y": 0,
            "z": 0,
            "xPercentage": 0,
            "yPercentage": 0
          }
        },
        "width": 1920,
        "height": 1080,
        "length": null
      },
      {
        "id": 1304195,
        "type": "photo",
        "isCover": false,
        "isNoticeCover": false,
        "isPreorderCover": false,
        "isCompleted": true,
        "isPreview": false,
        "previewVideoUri": null,
        "thumbnailUrl": null,
        "contentUrl": null,
        "visionResult": {
          "leftEye": {
            "x": 0,
            "y": 0,
            "z": 0,
            "xPercentage": 0,
            "yPercentage": 0
          },
          "rightEye": {
            "x": 0,
            "y": 0,
            "z": 0,
            "xPercentage": 0,
            "yPercentage": 0
          }
        },
        "width": 1920,
        "height": 1080,
        "length": null
      },
      {
        "id": 1304202,
        "type": "photo",
        "isCover": false,
        "isNoticeCover": false,
        "isPreorderCover": false,
        "isCompleted": true,
        "isPreview": false,
        "previewVideoUri": null,
        "thumbnailUrl": null,
        "contentUrl": null,
        "visionResult": {
          "leftEye": {
            "x": 0,
            "y": 0,
            "z": 0,
            "xPercentage": 0,
            "yPercentage": 0
          },
          "rightEye": {
            "x": 0,
            "y": 0,
            "z": 0,
            "xPercentage": 0,
            "yPercentage": 0
          }
        },
        "width": 1920,
        "height": 1080,
        "length": null
      },
      {
        "id": 1304199,
        "type": "photo",
        "isCover": false,
        "isNoticeCover": false,
        "isPreorderCover": false,
        "isCompleted": true,
        "isPreview": false,
        "previewVideoUri": null,
        "thumbnailUrl": null,
        "contentUrl": null,
        "visionResult": {
          "leftEye": {
            "x": 0,
            "y": 0,
            "z": 0,
            "xPercentage": 0,
            "yPercentage": 0
          },
          "rightEye": {
            "x": 0,
            "y": 0,
            "z": 0,
            "xPercentage": 0,
            "yPercentage": 0
          }
        },
        "width": 1920,
        "height": 1080,
        "length": null
      },
      {
        "id": 1304207,
        "type": "photo",
        "isCover": false,
        "isNoticeCover": false,
        "isPreorderCover": false,
        "isCompleted": true,
        "isPreview": false,
        "previewVideoUri": null,
        "thumbnailUrl": null,
        "contentUrl": null,
        "visionResult": {
          "leftEye": {
            "x": 0,
            "y": 0,
            "z": 0,
            "xPercentage": 0,
            "yPercentage": 0
          },
          "rightEye": {
            "x": 0,
            "y": 0,
            "z": 0,
            "xPercentage": 0,
            "yPercentage": 0
          }
        },
        "width": 1920,
        "height": 1080,
        "length": null
      },
      {
        "id": 1304203,
        "type": "photo",
        "isCover": false,
        "isNoticeCover": false,
        "isPreorderCover": false,
        "isCompleted": true,
        "isPreview": false,
        "previewVideoUri": null,
        "thumbnailUrl": null,
        "contentUrl": null,
        "visionResult": {
          "leftEye": {
            "x": 0,
            "y": 0,
            "z": 0,
            "xPercentage": 0,
            "yPercentage": 0
          },
          "rightEye": {
            "x": 0,
            "y": 0,
            "z": 0,
            "xPercentage": 0,
            "yPercentage": 0
          }
        },
        "width": 1920,
        "height": 1080,
        "length": null
      },
      {
        "id": 1304201,
        "type": "photo",
        "isCover": false,
        "isNoticeCover": false,
        "isPreorderCover": false,
        "isCompleted": true,
        "isPreview": false,
        "previewVideoUri": null,
        "thumbnailUrl": null,
        "contentUrl": null,
        "visionResult": {
          "leftEye": {
            "x": 0,
            "y": 0,
            "z": 0,
            "xPercentage": 0,
            "yPercentage": 0
          },
          "rightEye": {
            "x": 0,
            "y": 0,
            "z": 0,
            "xPercentage": 0,
            "yPercentage": 0
          }
        },
        "width": 1920,
        "height": 1080,
        "length": null
      },
      {
        "id": 1304200,
        "type": "photo",
        "isCover": false,
        "isNoticeCover": false,
        "isPreorderCover": false,
        "isCompleted": true,
        "isPreview": false,
        "previewVideoUri": null,
        "thumbnailUrl": null,
        "contentUrl": null,
        "visionResult": {
          "leftEye": {
            "x": 0,
            "y": 0,
            "z": 0,
            "xPercentage": 0,
            "yPercentage": 0
          },
          "rightEye": {
            "x": 0,
            "y": 0,
            "z": 0,
            "xPercentage": 0,
            "yPercentage": 0
          }
        },
        "width": 1920,
        "height": 1080,
        "length": null
      },
      {
        "id": 1304206,
        "type": "photo",
        "isCover": false,
        "isNoticeCover": false,
        "isPreorderCover": false,
        "isCompleted": true,
        "isPreview": false,
        "previewVideoUri": null,
        "thumbnailUrl": null,
        "contentUrl": null,
        "visionResult": {
          "leftEye": {
            "x": 0,
            "y": 0,
            "z": 0,
            "xPercentage": 0,
            "yPercentage": 0
          },
          "rightEye": {
            "x": 0,
            "y": 0,
            "z": 0,
            "xPercentage": 0,
            "yPercentage": 0
          }
        },
        "width": 1920,
        "height": 1080,
        "length": null
      },
      {
        "id": 1304204,
        "type": "photo",
        "isCover": false,
        "isNoticeCover": false,
        "isPreorderCover": false,
        "isCompleted": true,
        "isPreview": false,
        "previewVideoUri": null,
        "thumbnailUrl": null,
        "contentUrl": null,
        "visionResult": {
          "leftEye": {
            "x": 0,
            "y": 0,
            "z": 0,
            "xPercentage": 0,
            "yPercentage": 0
          },
          "rightEye": {
            "x": 0,
            "y": 0,
            "z": 0,
            "xPercentage": 0,
            "yPercentage": 0
          }
        },
        "width": 1920,
        "height": 1080,
        "length": null
      },
      {
        "id": 1304194,
        "type": "photo",
        "isCover": false,
        "isNoticeCover": false,
        "isPreorderCover": false,
        "isCompleted": true,
        "isPreview": false,
        "previewVideoUri": null,
        "thumbnailUrl": null,
        "contentUrl": null,
        "visionResult": {
          "leftEye": {
            "x": 0,
            "y": 0,
            "z": 0,
            "xPercentage": 0,
            "yPercentage": 0
          },
          "rightEye": {
            "x": 0,
            "y": 0,
            "z": 0,
            "xPercentage": 0,
            "yPercentage": 0
          }
        },
        "width": 1920,
        "height": 1080,
        "length": null
      },
      {
        "id": 1304205,
        "type": "photo",
        "isCover": false,
        "isNoticeCover": false,
        "isPreorderCover": false,
        "isCompleted": true,
        "isPreview": false,
        "previewVideoUri": null,
        "thumbnailUrl": null,
        "contentUrl": null,
        "visionResult": {
          "leftEye": {
            "x": 0,
            "y": 0,
            "z": 0,
            "xPercentage": 0,
            "yPercentage": 0
          },
          "rightEye": {
            "x": 0,
            "y": 0,
            "z": 0,
            "xPercentage": 0,
            "yPercentage": 0
          }
        },
        "width": 1920,
        "height": 1080,
        "length": null
      },
      {
        "id": 1304193,
        "type": "photo",
        "isCover": false,
        "isNoticeCover": false,
        "isPreorderCover": false,
        "isCompleted": true,
        "isPreview": false,
        "previewVideoUri": null,
        "thumbnailUrl": null,
        "contentUrl": null,
        "visionResult": {
          "leftEye": {
            "x": 0,
            "y": 0,
            "z": 0,
            "xPercentage": 0,
            "yPercentage": 0
          },
          "rightEye": {
            "x": 0,
            "y": 0,
            "z": 0,
            "xPercentage": 0,
            "yPercentage": 0
          }
        },
        "width": 1920,
        "height": 1080,
        "length": null
      },
      {
        "id": 1304186,
        "type": "photo",
        "isCover": false,
        "isNoticeCover": false,
        "isPreorderCover": false,
        "isCompleted": true,
        "isPreview": false,
        "previewVideoUri": null,
        "thumbnailUrl": null,
        "contentUrl": null,
        "visionResult": {
          "leftEye": {
            "x": 0,
            "y": 0,
            "z": 0,
            "xPercentage": 0,
            "yPercentage": 0
          },
          "rightEye": {
            "x": 0,
            "y": 0,
            "z": 0,
            "xPercentage": 0,
            "yPercentage": 0
          }
        },
        "width": 1920,
        "height": 1080,
        "length": null
      },
      {
        "id": 1304192,
        "type": "photo",
        "isCover": false,
        "isNoticeCover": false,
        "isPreorderCover": false,
        "isCompleted": true,
        "isPreview": false,
        "previewVideoUri": null,
        "thumbnailUrl": null,
        "contentUrl": null,
        "visionResult": {
          "leftEye": {
            "x": 0,
            "y": 0,
            "z": 0,
            "xPercentage": 0,
            "yPercentage": 0
          },
          "rightEye": {
            "x": 0,
            "y": 0,
            "z": 0,
            "xPercentage": 0,
            "yPercentage": 0
          }
        },
        "width": 1920,
        "height": 1080,
        "length": null
      },
      {
        "id": 1304190,
        "type": "photo",
        "isCover": false,
        "isNoticeCover": false,
        "isPreorderCover": false,
        "isCompleted": true,
        "isPreview": false,
        "previewVideoUri": null,
        "thumbnailUrl": null,
        "contentUrl": null,
        "visionResult": {
          "leftEye": {
            "x": 0,
            "y": 0,
            "z": 0,
            "xPercentage": 0,
            "yPercentage": 0
          },
          "rightEye": {
            "x": 0,
            "y": 0,
            "z": 0,
            "xPercentage": 0,
            "yPercentage": 0
          }
        },
        "width": 1920,
        "height": 1080,
        "length": null
      },
      {
        "id": 1304188,
        "type": "photo",
        "isCover": false,
        "isNoticeCover": false,
        "isPreorderCover": false,
        "isCompleted": true,
        "isPreview": false,
        "previewVideoUri": null,
        "thumbnailUrl": null,
        "contentUrl": null,
        "visionResult": {
          "leftEye": {
            "x": 0,
            "y": 0,
            "z": 0,
            "xPercentage": 0,
            "yPercentage": 0
          },
          "rightEye": {
            "x": 0,
            "y": 0,
            "z": 0,
            "xPercentage": 0,
            "yPercentage": 0
          }
        },
        "width": 1920,
        "height": 1080,
        "length": null
      }
    ]
  },
  "header": {
    "translateStatus": "completed",
    "contractUrlList": [],
    "canViewAnalytics": false,
    "canExamine": false,
    "canViewContract": false
  },
  "canShowTag": false,
  "canShowLog": false,
  "canShowTransferFileStatus": false,
  "canChangeLayoutMode": false
}