{
    "id": 15740,
    "category": "Pics",
    "publishCategory": "Pd",
    "layoutMode": "Published",
    "isCloudProduct": false,
    "title": "【雙模入湯】首次雙人誘惑，一起泡湯展現完美曲線 <陳婷+佐藤麻優>",
    "description": "<blockquote style=\"caret-color: rgb(115, 115, 115); color: rgb(115, 115, 115); font-family: &quot;Microsoft JhengHei&quot;;\">\n    <p style=\"margin-bottom: 0px; padding: 0px;\">【雙模入湯】日式雙人誘惑，帶你一步步進入泡湯世界 &lt;陳婷+佐藤麻優&gt;</p><p style=\"margin-bottom: 0px; padding: 0px;\"><br></p><p style=\"margin-bottom: 0px; padding: 0px;\">首次雙人拍攝</p><p style=\"margin-bottom: 0px; padding: 0px;\">歡迎多多支持</p>\n    <p style=\"margin-bottom: 0px; padding: 0px;\"><br></p>\n    <p style=\"padding: 0px;\"><span style=\"background-color: rgb(255, 255, 0);\">H 攝影師：<br></span><a href=\"https://www.jvid.com/H%E6%94%9D%E5%BD%B1\" class=\"linkified\" target=\"_blank\" rel=\"nofollow\" style=\"text-decoration: none; font-family: &quot;Microsoft JhengHei&quot;;\">https://www.jvid.com/H攝影</a><br>IG：<br><a href=\"https://www.instagram.com/h_sex_photo/\" target=\"_blank\">H攝影 IG</a></p><p style=\"padding: 0px;\"><a href=\"https://www.instagram.com/h_sex_photo/\" class=\"linkified\" target=\"_blank\" rel=\"nofollow\" style=\"text-decoration: none; font-family: &quot;Microsoft JhengHei&quot;;\"></a><br><span style=\"background-color: rgb(255, 255, 0);\">H攝影師作品集<br></span>------------------&nbsp;<br><a href=\"https://www.jvid.com/v/8oqd6YkR\" target=\"_blank\">終於約到女神泡湯，浴巾一直掉，最後不穿了直接拍 辰辰</a><br><br><a href=\"https://www.jvid.com/v/low86mXO\" target=\"_blank\" style=\"text-decoration: none;\">女神主動約泡湯， 完美線條若隱若現好誘人，&lt;性感女神-靜川奈&gt;</a><br><br><a href=\"https://www.jvid.com/v/JoBNDRoy\" target=\"_blank\" style=\"text-decoration: none;\">把學生妹綁起來調教，結果變得比攝影師還色 &lt;黎穎/全裸無遮/學生&gt;</a><br><br><a href=\"https://www.jvid.com/v/y15VRek7\" target=\"_blank\">【全裸三點無碼】雪白酥胸-白思言 陪你全裸泡美人湯</a><br><br><a href=\"https://www.jvid.com/v/4XgwDgXp\" target=\"_blank\" style=\"text-decoration: none;\">【全裸三點無碼】純情小妹妹泡湯寫真，最後全裸一絲不掛超誘人&lt;黎妍&gt;</a><br><br><a href=\"https://www.jvid.com/v/zkP5lYod\" target=\"_blank\">【全裸三點無碼】待嫁新娘床等你 11分鐘洗澡長片&lt;凌玉婷&gt;</a><br><br><a href=\"https://www.jvid.com/v/lobPjD1W\" target=\"_blank\" style=\"text-decoration: none;\">【新人上線】完美身材溫泉寫真，健美女神跟妳一起泡湯&lt;雅雅&gt;</a><br><br><a href=\"https://www.jvid.com/v/akllz5kV\" target=\"_blank\" style=\"text-decoration: none;\">神級新人Coser空姐帶你飛，內含13min絲襪＋洗澡長片&lt;吳紫欣&gt;</a></p>\n</blockquote>\n<blockquote style=\"caret-color: rgb(115, 115, 115); color: rgb(115, 115, 115); font-family: &quot;Microsoft JhengHei&quot;;\"><a href=\"https://www.jvid.com/v/akllz5kV\" target=\"_blank\" style=\"text-decoration: none; font-family: sans-serif;\">【全裸三點無碼】下班長腿OL 凡妮莎陪你洗香香!</a></blockquote>\n<blockquote style=\"caret-color: rgb(115, 115, 115); color: rgb(115, 115, 115); font-family: &quot;Microsoft JhengHei&quot;;\">\n    <p><a href=\"https://www.jvid.com/v/QoJgKdXb\" target=\"_blank\">女神首次激凸死庫水，野外大膽秀曲線 辰辰</a></p>\n    <p><br></p>\n    <h3 style=\"font-family: &quot;Microsoft JhengHei&quot;; line-height: 25px; color: rgb(51, 51, 51); margin-right: 0px; margin-bottom: 0px; margin-left: 0px; font-size: 20px;\"><a href=\"https://www.jvid.com/v/3k0YMrow\" target=\"_blank\">【全裸三點無碼】稚嫩美少女韓棠，等不及拍照，直接拉你一起洗香香拍影片</a><span style=\"font-size: 17.5px;\"></span></h3>\n</blockquote>",
    "price": 13.99,
    "discountPrice": null,
    "hiddenProductId": null,
    "hiddenPrice": null,
    "diamondPrice": 7000,
    "cover": {
        "thumbnail": "/minify_image/1600/3/1622370410787_294704/2021/05/30/0455f024fa915f0873bd74d09235bb03dc8dede0af395c9564a2f6abb48a15af.jpg",
        "video": "",
        "type": "photo",
        "ogImage": "/minify_image/1600/3/1622370410787_294704/2021/05/30/0455f024fa915f0873bd74d09235bb03dc8dede0af395c9564a2f6abb48a15af.jpg",
        "isCompleted": true
    },
    "photoCount": 82,
    "videoLength": "00:03:52",
    "viewTimes": 10392,
    "favoriteTimes": 62,
    "publishStart": 1622383200000,
    "buyButtonType": "notLogin",
    "bulkButtonType": "hide",
    "tag": [{
            "parentTagId": null,
            "color": "#2196f3",
            "nameI18nKey": "tag.nippleCovers",
            "id": 78,
            "type": "Boundary"
        },
        {
            "parentTagId": "123",
            "color": "#bebebe",
            "nameI18nKey": "tag.models",
            "id": 124,
            "type": "Genre"
        }
    ],
    "author": {
        "avatarUrl": "/rescale_avatar/1612373914510_294704/2021/02/04/18fea23353f540505280153328b94e2800d01d80711405b96904944da40fec9b_large.jpg",
        "displayName": "H 攝影師",
        "name": "H攝影",
        "id": 294704
    },
    "presenter": null,
    "producer": null,
    "collaborator": null,
    "crewList": [],
    "modelList": [{
            "avatarUrl": "/rescale_avatar/1631017711912_91978/2021/09/07/31782b9494c90d04fe6d86ffc349e2cf84c4c7aae44dfa9f0cc03458370bec64_large.jpg",
            "displayName": "陳婷",
            "name": "陳婷",
            "id": 91978
        },
        {
            "avatarUrl": "/rescale_avatar/1622474470943_42901/2021/05/31/06a7af81453b869de596a7b6ecbbc44d7d22801b6733c5d4681f396201c80c01_large.jpg",
            "displayName": "佐藤麻優",
            "name": "佐藤麻優",
            "id": 42901
        }
    ],
    "recommendVideo": [{
            "id": "YoNN0jo3",
            "category": "OfficialVids",
            "title": "飽滿E奶！俄羅斯混血女神「陳婷」大膽誘惑！",
            "coverImage": "/video_thumbnail/1624328709728_221868/2021/06/22/640/0e4b2593b887462508ad8ab8f4c8363c79f1371960e97bee4844ab8af9b2fe2e.jpg",
            "coverVideo": "/marked_preview_video/1624328709728_221868/2021/06/22/0e4b2593b887462508ad8ab8f4c8363c79f1371960e97bee4844ab8af9b2fe2e.mp4",
            "coverPreviewable": true,
            "originalPrice": 19.99,
            "specialPrice": 10.99,
            "favoriteTimes": 5,
            "viewTimes": 2354,
            "publishStart": 1624406402000,
            "photoCount": 0,
            "videoLength": "00:04:48",
            "hiddenVersionPhotoCount": 0,
            "hiddenVersionVideoLength": null,
            "model": [{
                "id": 91978,
                "name": "陳婷",
                "displayName": "陳婷",
                "avatarUrl": "/rescale_avatar/1631017711912_91978/2021/09/07/31782b9494c90d04fe6d86ffc349e2cf84c4c7aae44dfa9f0cc03458370bec64_small.jpg"
            }]
        },
        {
            "id": "p12r8z1x",
            "category": "Pics",
            "title": "@佐藤麻優@【第一本寫真集上線了】內附寫真書未公開的照片喔!趕快收藏。上架7天內購買送影片@@獨角獸@@誏你獸性大發...",
            "coverImage": "/minify_image/300/1624436557651_8403/2021/06/23/70960e95e1dfa6a8adda8545119b3a96157a0ed0818f9bcafddc87ad77efb605.jpg",
            "coverVideo": null,
            "coverPreviewable": false,
            "originalPrice": 10.99,
            "specialPrice": null,
            "favoriteTimes": 15,
            "viewTimes": 3233,
            "publishStart": 1624446000000,
            "photoCount": 116,
            "videoLength": null,
            "hiddenVersionPhotoCount": 0,
            "hiddenVersionVideoLength": null,
            "model": [{
                "id": 42901,
                "name": "佐藤麻優",
                "displayName": "佐藤麻優",
                "avatarUrl": "/rescale_avatar/1622474470943_42901/2021/05/31/06a7af81453b869de596a7b6ecbbc44d7d22801b6733c5d4681f396201c80c01_small.jpg"
            }]
        },
        {
            "id": "OXD5xG18",
            "category": "OfficialVids",
            "title": "混血女神「陳婷」長腿誘惑！情趣戰袍挺巨乳翹臀",
            "coverImage": "/video_thumbnail/1624458045300_221868/2021/06/23/640/9c8031d4fed127d9fa05f618cdaef88b73d22fa99111238d77b927695160ced8.jpg",
            "coverVideo": "/marked_preview_video/1624458045300_221868/2021/06/23/9c8031d4fed127d9fa05f618cdaef88b73d22fa99111238d77b927695160ced8.mp4",
            "coverPreviewable": true,
            "originalPrice": 19.99,
            "specialPrice": 10.99,
            "favoriteTimes": 3,
            "viewTimes": 1644,
            "publishStart": 1624665602000,
            "photoCount": 0,
            "videoLength": "00:04:21",
            "hiddenVersionPhotoCount": 0,
            "hiddenVersionVideoLength": null,
            "model": [{
                "id": 91978,
                "name": "陳婷",
                "displayName": "陳婷",
                "avatarUrl": "/rescale_avatar/1631017711912_91978/2021/09/07/31782b9494c90d04fe6d86ffc349e2cf84c4c7aae44dfa9f0cc03458370bec64_small.jpg"
            }]
        },
        {
            "id": "3XAVDG1O",
            "category": "OfficialVids",
            "title": "曖昧勾引！陳婷「超撩人誘惑」！",
            "coverImage": "/video_thumbnail/1624534053547_221868/2021/06/24/640/58e8d55279ffbf212440602479ffb43aac8dcb6333c22b68e2198ac70015141c.jpg",
            "coverVideo": "/marked_preview_video/1624534053547_221868/2021/06/24/58e8d55279ffbf212440602479ffb43aac8dcb6333c22b68e2198ac70015141c.mp4",
            "coverPreviewable": true,
            "originalPrice": 19.99,
            "specialPrice": 10.99,
            "favoriteTimes": 1,
            "viewTimes": 630,
            "publishStart": 1624924800000,
            "photoCount": 0,
            "videoLength": "00:04:17",
            "hiddenVersionPhotoCount": 0,
            "hiddenVersionVideoLength": null,
            "model": [{
                "id": 91978,
                "name": "陳婷",
                "displayName": "陳婷",
                "avatarUrl": "/rescale_avatar/1631017711912_91978/2021/09/07/31782b9494c90d04fe6d86ffc349e2cf84c4c7aae44dfa9f0cc03458370bec64_small.jpg"
            }]
        },
        {
            "id": "8oq5QmoR",
            "category": "OfficialVids",
            "title": "魔鬼曲線！混血美人「陳婷」美汝長腿太銷魂！",
            "coverImage": "/video_thumbnail/1624955766591_221868/2021/06/29/640/4becca6a978d6737df60ad693be2f06b743fe105c8829e317ed2d5940dfcc762.jpg",
            "coverVideo": "/marked_preview_video/1624955766591_221868/2021/06/29/4becca6a978d6737df60ad693be2f06b743fe105c8829e317ed2d5940dfcc762.mp4",
            "coverPreviewable": true,
            "originalPrice": 19.99,
            "specialPrice": 10.99,
            "favoriteTimes": 0,
            "viewTimes": 697,
            "publishStart": 1625097603000,
            "photoCount": 0,
            "videoLength": "00:05:03",
            "hiddenVersionPhotoCount": 0,
            "hiddenVersionVideoLength": null,
            "model": [{
                "id": 91978,
                "name": "陳婷",
                "displayName": "陳婷",
                "avatarUrl": "/rescale_avatar/1631017711912_91978/2021/09/07/31782b9494c90d04fe6d86ffc349e2cf84c4c7aae44dfa9f0cc03458370bec64_small.jpg"
            }]
        }
    ],
    "recommendModel": [{
            "avatarUrl": "/rescale_avatar/1594353820312_224213/2020/07/10/d9712b9e11b06e428c3f151bf4f580408031e89d3c95473db48df4834e26709d_large.jpg",
            "displayName": "キキkiki",
            "name": "キキkiki",
            "id": 224213
        },
        {
            "avatarUrl": "/rescale_avatar/1672842341447_616721/2023/01/04/cf370223a24aceb89f305335b149e6683437510bdb604169e490821460e5d6d3_large.jpeg",
            "displayName": "Bebe520",
            "name": "Bebe520",
            "id": 616721
        },
        {
            "avatarUrl": "/rescale_avatar/1642867132523_403625/2022/01/22/fa1351bf41e202c42241841b10049f7a9fb8d4513b25961674e93def338e8ed4_large.jpg",
            "displayName": "Chloe_lin",
            "name": "Chloe_lin",
            "id": 403625
        },
        {
            "avatarUrl": "/rescale_avatar/1560306142672_1006/2019/06/12/afb253070712407afbdf4632ac5a5bb154750a727a6f2e44ed9acf1765163642_large.jpg",
            "displayName": "RuoMa",
            "name": "RuoMa",
            "id": 117447
        },
        {
            "avatarUrl": "/rescale_avatar/1679225661377_323936/2023/03/19/73386ad76400d41e74f9b13700515c0cfcee9c8b596618adb568f9e6cad003ec_large.jpeg",
            "displayName": "酸酸Enny",
            "name": "酸酸Enny",
            "id": 323936
        },
        {
            "avatarUrl": "/rescale_avatar/1635838819823_465161/2021/11/02/a5662d387f9f0fcfcc554dde86b5327ad125d105fdd8dde1fce2f462d933c36f_large.jpg",
            "displayName": "白雪蘿綝",
            "name": "白雪蘿綝",
            "id": 465161
        },
        {
            "avatarUrl": "/rescale_avatar/1579805875318_32569/2020/01/24/e2fb6266821fa55dc208c479806aa2fdac10955ee75b06860c41f748ee465572_large.jpg",
            "displayName": "千雯",
            "name": "Cara850513",
            "id": 32569
        },
        {
            "avatarUrl": "/rescale_avatar/1644914849314_327318/2022/02/15/effe18e1746acebb17732f3f627754b9856e07bbfedbf1319871ea3baee4f60f_large.jpg",
            "displayName": "李靜",
            "name": "李靜",
            "id": 327318
        }
    ],
    "productMedia": {
        "hiddenProductFree": [],
        "hiddenProductPaid": [],
        "main": [{
                "id": 757153,
                "type": "photo",
                "isCover": true,
                "isNoticeCover": false,
                "isPreorderCover": false,
                "isCompleted": true,
                "isPreview": true,
                "previewVideoUri": null,
                "thumbnailUrl": "/minify_image/300/1622370410787_294704/2021/05/30/0455f024fa915f0873bd74d09235bb03dc8dede0af395c9564a2f6abb48a15af.jpg",
                "contentUrl": "/minify_image/1600/3/1622370410787_294704/2021/05/30/0455f024fa915f0873bd74d09235bb03dc8dede0af395c9564a2f6abb48a15af.jpg",
                "visionResult": {
                    "leftEye": {
                        "x": 0,
                        "y": 0,
                        "z": 0,
                        "xPercentage": 0,
                        "yPercentage": 0
                    },
                    "rightEye": {
                        "x": 0,
                        "y": 0,
                        "z": 0,
                        "xPercentage": 0,
                        "yPercentage": 0
                    }
                },
                "width": 1920,
                "height": 1080,
                "length": null
            },
            {
                "id": 15677,
                "type": "video",
                "isCover": false,
                "isNoticeCover": false,
                "isPreorderCover": false,
                "isCompleted": true,
                "isPreview": true,
                "previewVideoUri": "/marked_preview_video/1622370410787_294704/2021/05/30/e2aff62f785b682d992d023c8677a5a009596cb344edddcda5d8cbf69a605a37.mp4",
                "thumbnailUrl": "/video_thumbnail/1622370410787_294704/2021/05/30/e2aff62f785b682d992d023c8677a5a009596cb344edddcda5d8cbf69a605a37.jpg",
                "contentUrl": "/marked_preview_video/1622370410787_294704/2021/05/30/e2aff62f785b682d992d023c8677a5a009596cb344edddcda5d8cbf69a605a37.mp4",
                "visionResult": {
                    "leftEye": {
                        "x": 0,
                        "y": 0,
                        "z": 0,
                        "xPercentage": 0,
                        "yPercentage": 0
                    },
                    "rightEye": {
                        "x": 0,
                        "y": 0,
                        "z": 0,
                        "xPercentage": 0,
                        "yPercentage": 0
                    }
                },
                "width": 3840,
                "height": 2160,
                "length": "00:00:10"
            },
            {
                "id": 756684,
                "type": "photo",
                "isCover": false,
                "isNoticeCover": false,
                "isPreorderCover": false,
                "isCompleted": true,
                "isPreview": true,
                "previewVideoUri": null,
                "thumbnailUrl": "/minify_image/300/1622370410787_294704/2021/05/30/ba64402cf4b6fd9fcbc4276a37ebf573bacce031c8efc9015d51699803bee04d.jpg",
                "contentUrl": "/minify_image/1600/3/1622370410787_294704/2021/05/30/ba64402cf4b6fd9fcbc4276a37ebf573bacce031c8efc9015d51699803bee04d.jpg",
                "visionResult": {
                    "leftEye": {
                        "x": 0,
                        "y": 0,
                        "z": 0,
                        "xPercentage": 0,
                        "yPercentage": 0
                    },
                    "rightEye": {
                        "x": 0,
                        "y": 0,
                        "z": 0,
                        "xPercentage": 0,
                        "yPercentage": 0
                    }
                },
                "width": 1920,
                "height": 1080,
                "length": null
            },
            {
                "id": 756682,
                "type": "photo",
                "isCover": false,
                "isNoticeCover": false,
                "isPreorderCover": false,
                "isCompleted": true,
                "isPreview": true,
                "previewVideoUri": null,
                "thumbnailUrl": "/minify_image/300/1622370410787_294704/2021/05/30/77a2598e59e391c4bac77f076878d0520bd9d9b151875266b5e8ffb9c356002a.jpg",
                "contentUrl": "/minify_image/1600/3/1622370410787_294704/2021/05/30/77a2598e59e391c4bac77f076878d0520bd9d9b151875266b5e8ffb9c356002a.jpg",
                "visionResult": {
                    "leftEye": {
                        "x": 0,
                        "y": 0,
                        "z": 0,
                        "xPercentage": 0,
                        "yPercentage": 0
                    },
                    "rightEye": {
                        "x": 0,
                        "y": 0,
                        "z": 0,
                        "xPercentage": 0,
                        "yPercentage": 0
                    }
                },
                "width": 1920,
                "height": 1080,
                "length": null
            },
            {
                "id": 756653,
                "type": "photo",
                "isCover": false,
                "isNoticeCover": false,
                "isPreorderCover": false,
                "isCompleted": true,
                "isPreview": true,
                "previewVideoUri": null,
                "thumbnailUrl": "/minify_image/300/1622370410787_294704/2021/05/30/82d78729ff3df34f140b94bf48a6554a6aefcc41b1536e6f9ad24f3a5b046996.jpg",
                "contentUrl": "/minify_image/1600/3/1622370410787_294704/2021/05/30/82d78729ff3df34f140b94bf48a6554a6aefcc41b1536e6f9ad24f3a5b046996.jpg",
                "visionResult": {
                    "leftEye": {
                        "x": 0,
                        "y": 0,
                        "z": 0,
                        "xPercentage": 0,
                        "yPercentage": 0
                    },
                    "rightEye": {
                        "x": 0,
                        "y": 0,
                        "z": 0,
                        "xPercentage": 0,
                        "yPercentage": 0
                    }
                },
                "width": 1920,
                "height": 1080,
                "length": null
            },
            {
                "id": 756661,
                "type": "photo",
                "isCover": false,
                "isNoticeCover": false,
                "isPreorderCover": false,
                "isCompleted": true,
                "isPreview": false,
                "previewVideoUri": null,
                "thumbnailUrl": null,
                "contentUrl": null,
                "visionResult": {
                    "leftEye": {
                        "x": 0,
                        "y": 0,
                        "z": 0,
                        "xPercentage": 0,
                        "yPercentage": 0
                    },
                    "rightEye": {
                        "x": 0,
                        "y": 0,
                        "z": 0,
                        "xPercentage": 0,
                        "yPercentage": 0
                    }
                },
                "width": 1920,
                "height": 1080,
                "length": null
            },
            {
                "id": 756700,
                "type": "photo",
                "isCover": false,
                "isNoticeCover": false,
                "isPreorderCover": false,
                "isCompleted": true,
                "isPreview": false,
                "previewVideoUri": null,
                "thumbnailUrl": null,
                "contentUrl": null,
                "visionResult": {
                    "leftEye": {
                        "x": 0,
                        "y": 0,
                        "z": 0,
                        "xPercentage": 0,
                        "yPercentage": 0
                    },
                    "rightEye": {
                        "x": 0,
                        "y": 0,
                        "z": 0,
                        "xPercentage": 0,
                        "yPercentage": 0
                    }
                },
                "width": 1920,
                "height": 1080,
                "length": null
            },
            {
                "id": 756711,
                "type": "photo",
                "isCover": false,
                "isNoticeCover": false,
                "isPreorderCover": false,
                "isCompleted": true,
                "isPreview": false,
                "previewVideoUri": null,
                "thumbnailUrl": null,
                "contentUrl": null,
                "visionResult": {
                    "leftEye": {
                        "x": 0,
                        "y": 0,
                        "z": 0,
                        "xPercentage": 0,
                        "yPercentage": 0
                    },
                    "rightEye": {
                        "x": 0,
                        "y": 0,
                        "z": 0,
                        "xPercentage": 0,
                        "yPercentage": 0
                    }
                },
                "width": 1920,
                "height": 1080,
                "length": null
            },
            {
                "id": 756712,
                "type": "photo",
                "isCover": false,
                "isNoticeCover": false,
                "isPreorderCover": false,
                "isCompleted": true,
                "isPreview": false,
                "previewVideoUri": null,
                "thumbnailUrl": null,
                "contentUrl": null,
                "visionResult": {
                    "leftEye": {
                        "x": 0,
                        "y": 0,
                        "z": 0,
                        "xPercentage": 0,
                        "yPercentage": 0
                    },
                    "rightEye": {
                        "x": 0,
                        "y": 0,
                        "z": 0,
                        "xPercentage": 0,
                        "yPercentage": 0
                    }
                },
                "width": 1920,
                "height": 1080,
                "length": null
            },
            {
                "id": 756704,
                "type": "photo",
                "isCover": false,
                "isNoticeCover": false,
                "isPreorderCover": false,
                "isCompleted": true,
                "isPreview": false,
                "previewVideoUri": null,
                "thumbnailUrl": null,
                "contentUrl": null,
                "visionResult": {
                    "leftEye": {
                        "x": 0,
                        "y": 0,
                        "z": 0,
                        "xPercentage": 0,
                        "yPercentage": 0
                    },
                    "rightEye": {
                        "x": 0,
                        "y": 0,
                        "z": 0,
                        "xPercentage": 0,
                        "yPercentage": 0
                    }
                },
                "width": 1920,
                "height": 1080,
                "length": null
            },
            {
                "id": 756698,
                "type": "photo",
                "isCover": false,
                "isNoticeCover": false,
                "isPreorderCover": false,
                "isCompleted": true,
                "isPreview": false,
                "previewVideoUri": null,
                "thumbnailUrl": null,
                "contentUrl": null,
                "visionResult": {
                    "leftEye": {
                        "x": 0,
                        "y": 0,
                        "z": 0,
                        "xPercentage": 0,
                        "yPercentage": 0
                    },
                    "rightEye": {
                        "x": 0,
                        "y": 0,
                        "z": 0,
                        "xPercentage": 0,
                        "yPercentage": 0
                    }
                },
                "width": 1920,
                "height": 1080,
                "length": null
            },
            {
                "id": 756691,
                "type": "photo",
                "isCover": false,
                "isNoticeCover": false,
                "isPreorderCover": false,
                "isCompleted": true,
                "isPreview": false,
                "previewVideoUri": null,
                "thumbnailUrl": null,
                "contentUrl": null,
                "visionResult": {
                    "leftEye": {
                        "x": 0,
                        "y": 0,
                        "z": 0,
                        "xPercentage": 0,
                        "yPercentage": 0
                    },
                    "rightEye": {
                        "x": 0,
                        "y": 0,
                        "z": 0,
                        "xPercentage": 0,
                        "yPercentage": 0
                    }
                },
                "width": 1920,
                "height": 1080,
                "length": null
            },
            {
                "id": 756707,
                "type": "photo",
                "isCover": false,
                "isNoticeCover": false,
                "isPreorderCover": false,
                "isCompleted": true,
                "isPreview": false,
                "previewVideoUri": null,
                "thumbnailUrl": null,
                "contentUrl": null,
                "visionResult": {
                    "leftEye": {
                        "x": 0,
                        "y": 0,
                        "z": 0,
                        "xPercentage": 0,
                        "yPercentage": 0
                    },
                    "rightEye": {
                        "x": 0,
                        "y": 0,
                        "z": 0,
                        "xPercentage": 0,
                        "yPercentage": 0
                    }
                },
                "width": 1920,
                "height": 1080,
                "length": null
            },
            {
                "id": 756710,
                "type": "photo",
                "isCover": false,
                "isNoticeCover": false,
                "isPreorderCover": false,
                "isCompleted": true,
                "isPreview": false,
                "previewVideoUri": null,
                "thumbnailUrl": null,
                "contentUrl": null,
                "visionResult": {
                    "leftEye": {
                        "x": 0,
                        "y": 0,
                        "z": 0,
                        "xPercentage": 0,
                        "yPercentage": 0
                    },
                    "rightEye": {
                        "x": 0,
                        "y": 0,
                        "z": 0,
                        "xPercentage": 0,
                        "yPercentage": 0
                    }
                },
                "width": 1920,
                "height": 1080,
                "length": null
            },
            {
                "id": 756687,
                "type": "photo",
                "isCover": false,
                "isNoticeCover": false,
                "isPreorderCover": false,
                "isCompleted": true,
                "isPreview": false,
                "previewVideoUri": null,
                "thumbnailUrl": null,
                "contentUrl": null,
                "visionResult": {
                    "leftEye": {
                        "x": 0,
                        "y": 0,
                        "z": 0,
                        "xPercentage": 0,
                        "yPercentage": 0
                    },
                    "rightEye": {
                        "x": 0,
                        "y": 0,
                        "z": 0,
                        "xPercentage": 0,
                        "yPercentage": 0
                    }
                },
                "width": 1920,
                "height": 1080,
                "length": null
            },
            {
                "id": 756668,
                "type": "photo",
                "isCover": false,
                "isNoticeCover": false,
                "isPreorderCover": false,
                "isCompleted": true,
                "isPreview": false,
                "previewVideoUri": null,
                "thumbnailUrl": null,
                "contentUrl": null,
                "visionResult": {
                    "leftEye": {
                        "x": 0,
                        "y": 0,
                        "z": 0,
                        "xPercentage": 0,
                        "yPercentage": 0
                    },
                    "rightEye": {
                        "x": 0,
                        "y": 0,
                        "z": 0,
                        "xPercentage": 0,
                        "yPercentage": 0
                    }
                },
                "width": 1920,
                "height": 1080,
                "length": null
            },
            {
                "id": 756713,
                "type": "photo",
                "isCover": false,
                "isNoticeCover": false,
                "isPreorderCover": false,
                "isCompleted": true,
                "isPreview": false,
                "previewVideoUri": null,
                "thumbnailUrl": null,
                "contentUrl": null,
                "visionResult": {
                    "leftEye": {
                        "x": 0,
                        "y": 0,
                        "z": 0,
                        "xPercentage": 0,
                        "yPercentage": 0
                    },
                    "rightEye": {
                        "x": 0,
                        "y": 0,
                        "z": 0,
                        "xPercentage": 0,
                        "yPercentage": 0
                    }
                },
                "width": 1920,
                "height": 1080,
                "length": null
            },
            {
                "id": 756697,
                "type": "photo",
                "isCover": false,
                "isNoticeCover": false,
                "isPreorderCover": false,
                "isCompleted": true,
                "isPreview": false,
                "previewVideoUri": null,
                "thumbnailUrl": null,
                "contentUrl": null,
                "visionResult": {
                    "leftEye": {
                        "x": 0,
                        "y": 0,
                        "z": 0,
                        "xPercentage": 0,
                        "yPercentage": 0
                    },
                    "rightEye": {
                        "x": 0,
                        "y": 0,
                        "z": 0,
                        "xPercentage": 0,
                        "yPercentage": 0
                    }
                },
                "width": 1920,
                "height": 1080,
                "length": null
            },
            {
                "id": 756709,
                "type": "photo",
                "isCover": false,
                "isNoticeCover": false,
                "isPreorderCover": false,
                "isCompleted": true,
                "isPreview": false,
                "previewVideoUri": null,
                "thumbnailUrl": null,
                "contentUrl": null,
                "visionResult": {
                    "leftEye": {
                        "x": 0,
                        "y": 0,
                        "z": 0,
                        "xPercentage": 0,
                        "yPercentage": 0
                    },
                    "rightEye": {
                        "x": 0,
                        "y": 0,
                        "z": 0,
                        "xPercentage": 0,
                        "yPercentage": 0
                    }
                },
                "width": 1920,
                "height": 1080,
                "length": null
            },
            {
                "id": 756688,
                "type": "photo",
                "isCover": false,
                "isNoticeCover": false,
                "isPreorderCover": false,
                "isCompleted": true,
                "isPreview": false,
                "previewVideoUri": null,
                "thumbnailUrl": null,
                "contentUrl": null,
                "visionResult": {
                    "leftEye": {
                        "x": 0,
                        "y": 0,
                        "z": 0,
                        "xPercentage": 0,
                        "yPercentage": 0
                    },
                    "rightEye": {
                        "x": 0,
                        "y": 0,
                        "z": 0,
                        "xPercentage": 0,
                        "yPercentage": 0
                    }
                },
                "width": 1920,
                "height": 1080,
                "length": null
            },
            {
                "id": 756703,
                "type": "photo",
                "isCover": false,
                "isNoticeCover": false,
                "isPreorderCover": false,
                "isCompleted": true,
                "isPreview": false,
                "previewVideoUri": null,
                "thumbnailUrl": null,
                "contentUrl": null,
                "visionResult": {
                    "leftEye": {
                        "x": 0,
                        "y": 0,
                        "z": 0,
                        "xPercentage": 0,
                        "yPercentage": 0
                    },
                    "rightEye": {
                        "x": 0,
                        "y": 0,
                        "z": 0,
                        "xPercentage": 0,
                        "yPercentage": 0
                    }
                },
                "width": 1920,
                "height": 1080,
                "length": null
            },
            {
                "id": 756701,
                "type": "photo",
                "isCover": false,
                "isNoticeCover": false,
                "isPreorderCover": false,
                "isCompleted": true,
                "isPreview": false,
                "previewVideoUri": null,
                "thumbnailUrl": null,
                "contentUrl": null,
                "visionResult": {
                    "leftEye": {
                        "x": 0,
                        "y": 0,
                        "z": 0,
                        "xPercentage": 0,
                        "yPercentage": 0
                    },
                    "rightEye": {
                        "x": 0,
                        "y": 0,
                        "z": 0,
                        "xPercentage": 0,
                        "yPercentage": 0
                    }
                },
                "width": 1920,
                "height": 1080,
                "length": null
            },
            {
                "id": 756706,
                "type": "photo",
                "isCover": false,
                "isNoticeCover": false,
                "isPreorderCover": false,
                "isCompleted": true,
                "isPreview": false,
                "previewVideoUri": null,
                "thumbnailUrl": null,
                "contentUrl": null,
                "visionResult": {
                    "leftEye": {
                        "x": 0,
                        "y": 0,
                        "z": 0,
                        "xPercentage": 0,
                        "yPercentage": 0
                    },
                    "rightEye": {
                        "x": 0,
                        "y": 0,
                        "z": 0,
                        "xPercentage": 0,
                        "yPercentage": 0
                    }
                },
                "width": 1920,
                "height": 1080,
                "length": null
            },
            {
                "id": 756658,
                "type": "photo",
                "isCover": false,
                "isNoticeCover": false,
                "isPreorderCover": false,
                "isCompleted": true,
                "isPreview": false,
                "previewVideoUri": null,
                "thumbnailUrl": null,
                "contentUrl": null,
                "visionResult": {
                    "leftEye": {
                        "x": 0,
                        "y": 0,
                        "z": 0,
                        "xPercentage": 0,
                        "yPercentage": 0
                    },
                    "rightEye": {
                        "x": 0,
                        "y": 0,
                        "z": 0,
                        "xPercentage": 0,
                        "yPercentage": 0
                    }
                },
                "width": 1920,
                "height": 1080,
                "length": null
            },
            {
                "id": 756699,
                "type": "photo",
                "isCover": false,
                "isNoticeCover": false,
                "isPreorderCover": false,
                "isCompleted": true,
                "isPreview": false,
                "previewVideoUri": null,
                "thumbnailUrl": null,
                "contentUrl": null,
                "visionResult": {
                    "leftEye": {
                        "x": 0,
                        "y": 0,
                        "z": 0,
                        "xPercentage": 0,
                        "yPercentage": 0
                    },
                    "rightEye": {
                        "x": 0,
                        "y": 0,
                        "z": 0,
                        "xPercentage": 0,
                        "yPercentage": 0
                    }
                },
                "width": 1920,
                "height": 1080,
                "length": null
            },
            {
                "id": 756696,
                "type": "photo",
                "isCover": false,
                "isNoticeCover": false,
                "isPreorderCover": false,
                "isCompleted": true,
                "isPreview": false,
                "previewVideoUri": null,
                "thumbnailUrl": null,
                "contentUrl": null,
                "visionResult": {
                    "leftEye": {
                        "x": 0,
                        "y": 0,
                        "z": 0,
                        "xPercentage": 0,
                        "yPercentage": 0
                    },
                    "rightEye": {
                        "x": 0,
                        "y": 0,
                        "z": 0,
                        "xPercentage": 0,
                        "yPercentage": 0
                    }
                },
                "width": 1920,
                "height": 1080,
                "length": null
            },
            {
                "id": 756690,
                "type": "photo",
                "isCover": false,
                "isNoticeCover": false,
                "isPreorderCover": false,
                "isCompleted": true,
                "isPreview": false,
                "previewVideoUri": null,
                "thumbnailUrl": null,
                "contentUrl": null,
                "visionResult": {
                    "leftEye": {
                        "x": 0,
                        "y": 0,
                        "z": 0,
                        "xPercentage": 0,
                        "yPercentage": 0
                    },
                    "rightEye": {
                        "x": 0,
                        "y": 0,
                        "z": 0,
                        "xPercentage": 0,
                        "yPercentage": 0
                    }
                },
                "width": 1920,
                "height": 1080,
                "length": null
            },
            {
                "id": 756692,
                "type": "photo",
                "isCover": false,
                "isNoticeCover": false,
                "isPreorderCover": false,
                "isCompleted": true,
                "isPreview": false,
                "previewVideoUri": null,
                "thumbnailUrl": null,
                "contentUrl": null,
                "visionResult": {
                    "leftEye": {
                        "x": 0,
                        "y": 0,
                        "z": 0,
                        "xPercentage": 0,
                        "yPercentage": 0
                    },
                    "rightEye": {
                        "x": 0,
                        "y": 0,
                        "z": 0,
                        "xPercentage": 0,
                        "yPercentage": 0
                    }
                },
                "width": 1920,
                "height": 1080,
                "length": null
            },
            {
                "id": 756702,
                "type": "photo",
                "isCover": false,
                "isNoticeCover": false,
                "isPreorderCover": false,
                "isCompleted": true,
                "isPreview": false,
                "previewVideoUri": null,
                "thumbnailUrl": null,
                "contentUrl": null,
                "visionResult": {
                    "leftEye": {
                        "x": 0,
                        "y": 0,
                        "z": 0,
                        "xPercentage": 0,
                        "yPercentage": 0
                    },
                    "rightEye": {
                        "x": 0,
                        "y": 0,
                        "z": 0,
                        "xPercentage": 0,
                        "yPercentage": 0
                    }
                },
                "width": 1920,
                "height": 1080,
                "length": null
            },
            {
                "id": 756708,
                "type": "photo",
                "isCover": false,
                "isNoticeCover": false,
                "isPreorderCover": false,
                "isCompleted": true,
                "isPreview": false,
                "previewVideoUri": null,
                "thumbnailUrl": null,
                "contentUrl": null,
                "visionResult": {
                    "leftEye": {
                        "x": 0,
                        "y": 0,
                        "z": 0,
                        "xPercentage": 0,
                        "yPercentage": 0
                    },
                    "rightEye": {
                        "x": 0,
                        "y": 0,
                        "z": 0,
                        "xPercentage": 0,
                        "yPercentage": 0
                    }
                },
                "width": 1920,
                "height": 1080,
                "length": null
            },
            {
                "id": 756705,
                "type": "photo",
                "isCover": false,
                "isNoticeCover": false,
                "isPreorderCover": false,
                "isCompleted": true,
                "isPreview": false,
                "previewVideoUri": null,
                "thumbnailUrl": null,
                "contentUrl": null,
                "visionResult": {
                    "leftEye": {
                        "x": 0,
                        "y": 0,
                        "z": 0,
                        "xPercentage": 0,
                        "yPercentage": 0
                    },
                    "rightEye": {
                        "x": 0,
                        "y": 0,
                        "z": 0,
                        "xPercentage": 0,
                        "yPercentage": 0
                    }
                },
                "width": 1920,
                "height": 1080,
                "length": null
            },
            {
                "id": 756683,
                "type": "photo",
                "isCover": false,
                "isNoticeCover": false,
                "isPreorderCover": false,
                "isCompleted": true,
                "isPreview": false,
                "previewVideoUri": null,
                "thumbnailUrl": null,
                "contentUrl": null,
                "visionResult": {
                    "leftEye": {
                        "x": 0,
                        "y": 0,
                        "z": 0,
                        "xPercentage": 0,
                        "yPercentage": 0
                    },
                    "rightEye": {
                        "x": 0,
                        "y": 0,
                        "z": 0,
                        "xPercentage": 0,
                        "yPercentage": 0
                    }
                },
                "width": 1920,
                "height": 1080,
                "length": null
            },
            {
                "id": 756675,
                "type": "photo",
                "isCover": false,
                "isNoticeCover": false,
                "isPreorderCover": false,
                "isCompleted": true,
                "isPreview": false,
                "previewVideoUri": null,
                "thumbnailUrl": null,
                "contentUrl": null,
                "visionResult": {
                    "leftEye": {
                        "x": 0,
                        "y": 0,
                        "z": 0,
                        "xPercentage": 0,
                        "yPercentage": 0
                    },
                    "rightEye": {
                        "x": 0,
                        "y": 0,
                        "z": 0,
                        "xPercentage": 0,
                        "yPercentage": 0
                    }
                },
                "width": 1920,
                "height": 1080,
                "length": null
            },
            {
                "id": 756678,
                "type": "photo",
                "isCover": false,
                "isNoticeCover": false,
                "isPreorderCover": false,
                "isCompleted": true,
                "isPreview": false,
                "previewVideoUri": null,
                "thumbnailUrl": null,
                "contentUrl": null,
                "visionResult": {
                    "leftEye": {
                        "x": 0,
                        "y": 0,
                        "z": 0,
                        "xPercentage": 0,
                        "yPercentage": 0
                    },
                    "rightEye": {
                        "x": 0,
                        "y": 0,
                        "z": 0,
                        "xPercentage": 0,
                        "yPercentage": 0
                    }
                },
                "width": 1920,
                "height": 1080,
                "length": null
            },
            {
                "id": 756670,
                "type": "photo",
                "isCover": false,
                "isNoticeCover": false,
                "isPreorderCover": false,
                "isCompleted": true,
                "isPreview": false,
                "previewVideoUri": null,
                "thumbnailUrl": null,
                "contentUrl": null,
                "visionResult": {
                    "leftEye": {
                        "x": 0,
                        "y": 0,
                        "z": 0,
                        "xPercentage": 0,
                        "yPercentage": 0
                    },
                    "rightEye": {
                        "x": 0,
                        "y": 0,
                        "z": 0,
                        "xPercentage": 0,
                        "yPercentage": 0
                    }
                },
                "width": 1920,
                "height": 1080,
                "length": null
            },
            {
                "id": 756667,
                "type": "photo",
                "isCover": false,
                "isNoticeCover": false,
                "isPreorderCover": false,
                "isCompleted": true,
                "isPreview": false,
                "previewVideoUri": null,
                "thumbnailUrl": null,
                "contentUrl": null,
                "visionResult": {
                    "leftEye": {
                        "x": 0,
                        "y": 0,
                        "z": 0,
                        "xPercentage": 0,
                        "yPercentage": 0
                    },
                    "rightEye": {
                        "x": 0,
                        "y": 0,
                        "z": 0,
                        "xPercentage": 0,
                        "yPercentage": 0
                    }
                },
                "width": 1920,
                "height": 1080,
                "length": null
            },
            {
                "id": 756679,
                "type": "photo",
                "isCover": false,
                "isNoticeCover": false,
                "isPreorderCover": false,
                "isCompleted": true,
                "isPreview": false,
                "previewVideoUri": null,
                "thumbnailUrl": null,
                "contentUrl": null,
                "visionResult": {
                    "leftEye": {
                        "x": 0,
                        "y": 0,
                        "z": 0,
                        "xPercentage": 0,
                        "yPercentage": 0
                    },
                    "rightEye": {
                        "x": 0,
                        "y": 0,
                        "z": 0,
                        "xPercentage": 0,
                        "yPercentage": 0
                    }
                },
                "width": 1920,
                "height": 1080,
                "length": null
            },
            {
                "id": 756662,
                "type": "photo",
                "isCover": false,
                "isNoticeCover": false,
                "isPreorderCover": false,
                "isCompleted": true,
                "isPreview": false,
                "previewVideoUri": null,
                "thumbnailUrl": null,
                "contentUrl": null,
                "visionResult": {
                    "leftEye": {
                        "x": 0,
                        "y": 0,
                        "z": 0,
                        "xPercentage": 0,
                        "yPercentage": 0
                    },
                    "rightEye": {
                        "x": 0,
                        "y": 0,
                        "z": 0,
                        "xPercentage": 0,
                        "yPercentage": 0
                    }
                },
                "width": 1920,
                "height": 1080,
                "length": null
            },
            {
                "id": 756634,
                "type": "photo",
                "isCover": false,
                "isNoticeCover": false,
                "isPreorderCover": false,
                "isCompleted": true,
                "isPreview": false,
                "previewVideoUri": null,
                "thumbnailUrl": null,
                "contentUrl": null,
                "visionResult": {
                    "leftEye": {
                        "x": 0,
                        "y": 0,
                        "z": 0,
                        "xPercentage": 0,
                        "yPercentage": 0
                    },
                    "rightEye": {
                        "x": 0,
                        "y": 0,
                        "z": 0,
                        "xPercentage": 0,
                        "yPercentage": 0
                    }
                },
                "width": 1920,
                "height": 1080,
                "length": null
            },
            {
                "id": 756669,
                "type": "photo",
                "isCover": false,
                "isNoticeCover": false,
                "isPreorderCover": false,
                "isCompleted": true,
                "isPreview": false,
                "previewVideoUri": null,
                "thumbnailUrl": null,
                "contentUrl": null,
                "visionResult": {
                    "leftEye": {
                        "x": 0,
                        "y": 0,
                        "z": 0,
                        "xPercentage": 0,
                        "yPercentage": 0
                    },
                    "rightEye": {
                        "x": 0,
                        "y": 0,
                        "z": 0,
                        "xPercentage": 0,
                        "yPercentage": 0
                    }
                },
                "width": 1920,
                "height": 1080,
                "length": null
            },
            {
                "id": 756689,
                "type": "photo",
                "isCover": false,
                "isNoticeCover": false,
                "isPreorderCover": false,
                "isCompleted": true,
                "isPreview": false,
                "previewVideoUri": null,
                "thumbnailUrl": null,
                "contentUrl": null,
                "visionResult": {
                    "leftEye": {
                        "x": 0,
                        "y": 0,
                        "z": 0,
                        "xPercentage": 0,
                        "yPercentage": 0
                    },
                    "rightEye": {
                        "x": 0,
                        "y": 0,
                        "z": 0,
                        "xPercentage": 0,
                        "yPercentage": 0
                    }
                },
                "width": 1920,
                "height": 1080,
                "length": null
            },
            {
                "id": 756666,
                "type": "photo",
                "isCover": false,
                "isNoticeCover": false,
                "isPreorderCover": false,
                "isCompleted": true,
                "isPreview": false,
                "previewVideoUri": null,
                "thumbnailUrl": null,
                "contentUrl": null,
                "visionResult": {
                    "leftEye": {
                        "x": 0,
                        "y": 0,
                        "z": 0,
                        "xPercentage": 0,
                        "yPercentage": 0
                    },
                    "rightEye": {
                        "x": 0,
                        "y": 0,
                        "z": 0,
                        "xPercentage": 0,
                        "yPercentage": 0
                    }
                },
                "width": 1920,
                "height": 1080,
                "length": null
            },
            {
                "id": 756695,
                "type": "photo",
                "isCover": false,
                "isNoticeCover": false,
                "isPreorderCover": false,
                "isCompleted": true,
                "isPreview": false,
                "previewVideoUri": null,
                "thumbnailUrl": null,
                "contentUrl": null,
                "visionResult": {
                    "leftEye": {
                        "x": 0,
                        "y": 0,
                        "z": 0,
                        "xPercentage": 0,
                        "yPercentage": 0
                    },
                    "rightEye": {
                        "x": 0,
                        "y": 0,
                        "z": 0,
                        "xPercentage": 0,
                        "yPercentage": 0
                    }
                },
                "width": 1920,
                "height": 1080,
                "length": null
            },
            {
                "id": 756686,
                "type": "photo",
                "isCover": false,
                "isNoticeCover": false,
                "isPreorderCover": false,
                "isCompleted": true,
                "isPreview": false,
                "previewVideoUri": null,
                "thumbnailUrl": null,
                "contentUrl": null,
                "visionResult": {
                    "leftEye": {
                        "x": 0,
                        "y": 0,
                        "z": 0,
                        "xPercentage": 0,
                        "yPercentage": 0
                    },
                    "rightEye": {
                        "x": 0,
                        "y": 0,
                        "z": 0,
                        "xPercentage": 0,
                        "yPercentage": 0
                    }
                },
                "width": 1920,
                "height": 1080,
                "length": null
            },
            {
                "id": 756677,
                "type": "photo",
                "isCover": false,
                "isNoticeCover": false,
                "isPreorderCover": false,
                "isCompleted": true,
                "isPreview": false,
                "previewVideoUri": null,
                "thumbnailUrl": null,
                "contentUrl": null,
                "visionResult": {
                    "leftEye": {
                        "x": 0,
                        "y": 0,
                        "z": 0,
                        "xPercentage": 0,
                        "yPercentage": 0
                    },
                    "rightEye": {
                        "x": 0,
                        "y": 0,
                        "z": 0,
                        "xPercentage": 0,
                        "yPercentage": 0
                    }
                },
                "width": 1920,
                "height": 1080,
                "length": null
            },
            {
                "id": 756676,
                "type": "photo",
                "isCover": false,
                "isNoticeCover": false,
                "isPreorderCover": false,
                "isCompleted": true,
                "isPreview": false,
                "previewVideoUri": null,
                "thumbnailUrl": null,
                "contentUrl": null,
                "visionResult": {
                    "leftEye": {
                        "x": 0,
                        "y": 0,
                        "z": 0,
                        "xPercentage": 0,
                        "yPercentage": 0
                    },
                    "rightEye": {
                        "x": 0,
                        "y": 0,
                        "z": 0,
                        "xPercentage": 0,
                        "yPercentage": 0
                    }
                },
                "width": 1920,
                "height": 1080,
                "length": null
            },
            {
                "id": 756693,
                "type": "photo",
                "isCover": false,
                "isNoticeCover": false,
                "isPreorderCover": false,
                "isCompleted": true,
                "isPreview": false,
                "previewVideoUri": null,
                "thumbnailUrl": null,
                "contentUrl": null,
                "visionResult": {
                    "leftEye": {
                        "x": 0,
                        "y": 0,
                        "z": 0,
                        "xPercentage": 0,
                        "yPercentage": 0
                    },
                    "rightEye": {
                        "x": 0,
                        "y": 0,
                        "z": 0,
                        "xPercentage": 0,
                        "yPercentage": 0
                    }
                },
                "width": 1920,
                "height": 1080,
                "length": null
            },
            {
                "id": 756681,
                "type": "photo",
                "isCover": false,
                "isNoticeCover": false,
                "isPreorderCover": false,
                "isCompleted": true,
                "isPreview": false,
                "previewVideoUri": null,
                "thumbnailUrl": null,
                "contentUrl": null,
                "visionResult": {
                    "leftEye": {
                        "x": 0,
                        "y": 0,
                        "z": 0,
                        "xPercentage": 0,
                        "yPercentage": 0
                    },
                    "rightEye": {
                        "x": 0,
                        "y": 0,
                        "z": 0,
                        "xPercentage": 0,
                        "yPercentage": 0
                    }
                },
                "width": 1920,
                "height": 1080,
                "length": null
            },
            {
                "id": 756640,
                "type": "photo",
                "isCover": false,
                "isNoticeCover": false,
                "isPreorderCover": false,
                "isCompleted": true,
                "isPreview": false,
                "previewVideoUri": null,
                "thumbnailUrl": null,
                "contentUrl": null,
                "visionResult": {
                    "leftEye": {
                        "x": 0,
                        "y": 0,
                        "z": 0,
                        "xPercentage": 0,
                        "yPercentage": 0
                    },
                    "rightEye": {
                        "x": 0,
                        "y": 0,
                        "z": 0,
                        "xPercentage": 0,
                        "yPercentage": 0
                    }
                },
                "width": 1920,
                "height": 1080,
                "length": null
            },
            {
                "id": 756663,
                "type": "photo",
                "isCover": false,
                "isNoticeCover": false,
                "isPreorderCover": false,
                "isCompleted": true,
                "isPreview": false,
                "previewVideoUri": null,
                "thumbnailUrl": null,
                "contentUrl": null,
                "visionResult": {
                    "leftEye": {
                        "x": 0,
                        "y": 0,
                        "z": 0,
                        "xPercentage": 0,
                        "yPercentage": 0
                    },
                    "rightEye": {
                        "x": 0,
                        "y": 0,
                        "z": 0,
                        "xPercentage": 0,
                        "yPercentage": 0
                    }
                },
                "width": 1920,
                "height": 1080,
                "length": null
            },
            {
                "id": 756673,
                "type": "photo",
                "isCover": false,
                "isNoticeCover": false,
                "isPreorderCover": false,
                "isCompleted": true,
                "isPreview": false,
                "previewVideoUri": null,
                "thumbnailUrl": null,
                "contentUrl": null,
                "visionResult": {
                    "leftEye": {
                        "x": 0,
                        "y": 0,
                        "z": 0,
                        "xPercentage": 0,
                        "yPercentage": 0
                    },
                    "rightEye": {
                        "x": 0,
                        "y": 0,
                        "z": 0,
                        "xPercentage": 0,
                        "yPercentage": 0
                    }
                },
                "width": 1920,
                "height": 1080,
                "length": null
            },
            {
                "id": 756674,
                "type": "photo",
                "isCover": false,
                "isNoticeCover": false,
                "isPreorderCover": false,
                "isCompleted": true,
                "isPreview": false,
                "previewVideoUri": null,
                "thumbnailUrl": null,
                "contentUrl": null,
                "visionResult": {
                    "leftEye": {
                        "x": 0,
                        "y": 0,
                        "z": 0,
                        "xPercentage": 0,
                        "yPercentage": 0
                    },
                    "rightEye": {
                        "x": 0,
                        "y": 0,
                        "z": 0,
                        "xPercentage": 0,
                        "yPercentage": 0
                    }
                },
                "width": 1920,
                "height": 1080,
                "length": null
            },
            {
                "id": 756672,
                "type": "photo",
                "isCover": false,
                "isNoticeCover": false,
                "isPreorderCover": false,
                "isCompleted": true,
                "isPreview": false,
                "previewVideoUri": null,
                "thumbnailUrl": null,
                "contentUrl": null,
                "visionResult": {
                    "leftEye": {
                        "x": 0,
                        "y": 0,
                        "z": 0,
                        "xPercentage": 0,
                        "yPercentage": 0
                    },
                    "rightEye": {
                        "x": 0,
                        "y": 0,
                        "z": 0,
                        "xPercentage": 0,
                        "yPercentage": 0
                    }
                },
                "width": 1920,
                "height": 1080,
                "length": null
            },
            {
                "id": 756685,
                "type": "photo",
                "isCover": false,
                "isNoticeCover": false,
                "isPreorderCover": false,
                "isCompleted": true,
                "isPreview": false,
                "previewVideoUri": null,
                "thumbnailUrl": null,
                "contentUrl": null,
                "visionResult": {
                    "leftEye": {
                        "x": 0,
                        "y": 0,
                        "z": 0,
                        "xPercentage": 0,
                        "yPercentage": 0
                    },
                    "rightEye": {
                        "x": 0,
                        "y": 0,
                        "z": 0,
                        "xPercentage": 0,
                        "yPercentage": 0
                    }
                },
                "width": 1920,
                "height": 1080,
                "length": null
            },
            {
                "id": 756664,
                "type": "photo",
                "isCover": false,
                "isNoticeCover": false,
                "isPreorderCover": false,
                "isCompleted": true,
                "isPreview": false,
                "previewVideoUri": null,
                "thumbnailUrl": null,
                "contentUrl": null,
                "visionResult": {
                    "leftEye": {
                        "x": 0,
                        "y": 0,
                        "z": 0,
                        "xPercentage": 0,
                        "yPercentage": 0
                    },
                    "rightEye": {
                        "x": 0,
                        "y": 0,
                        "z": 0,
                        "xPercentage": 0,
                        "yPercentage": 0
                    }
                },
                "width": 1920,
                "height": 1080,
                "length": null
            },
            {
                "id": 756671,
                "type": "photo",
                "isCover": false,
                "isNoticeCover": false,
                "isPreorderCover": false,
                "isCompleted": true,
                "isPreview": false,
                "previewVideoUri": null,
                "thumbnailUrl": null,
                "contentUrl": null,
                "visionResult": {
                    "leftEye": {
                        "x": 0,
                        "y": 0,
                        "z": 0,
                        "xPercentage": 0,
                        "yPercentage": 0
                    },
                    "rightEye": {
                        "x": 0,
                        "y": 0,
                        "z": 0,
                        "xPercentage": 0,
                        "yPercentage": 0
                    }
                },
                "width": 1920,
                "height": 1080,
                "length": null
            },
            {
                "id": 756665,
                "type": "photo",
                "isCover": false,
                "isNoticeCover": false,
                "isPreorderCover": false,
                "isCompleted": true,
                "isPreview": false,
                "previewVideoUri": null,
                "thumbnailUrl": null,
                "contentUrl": null,
                "visionResult": {
                    "leftEye": {
                        "x": 0,
                        "y": 0,
                        "z": 0,
                        "xPercentage": 0,
                        "yPercentage": 0
                    },
                    "rightEye": {
                        "x": 0,
                        "y": 0,
                        "z": 0,
                        "xPercentage": 0,
                        "yPercentage": 0
                    }
                },
                "width": 1920,
                "height": 1080,
                "length": null
            },
            {
                "id": 756694,
                "type": "photo",
                "isCover": false,
                "isNoticeCover": false,
                "isPreorderCover": false,
                "isCompleted": true,
                "isPreview": false,
                "previewVideoUri": null,
                "thumbnailUrl": null,
                "contentUrl": null,
                "visionResult": {
                    "leftEye": {
                        "x": 0,
                        "y": 0,
                        "z": 0,
                        "xPercentage": 0,
                        "yPercentage": 0
                    },
                    "rightEye": {
                        "x": 0,
                        "y": 0,
                        "z": 0,
                        "xPercentage": 0,
                        "yPercentage": 0
                    }
                },
                "width": 1920,
                "height": 1080,
                "length": null
            },
            {
                "id": 756680,
                "type": "photo",
                "isCover": false,
                "isNoticeCover": false,
                "isPreorderCover": false,
                "isCompleted": true,
                "isPreview": false,
                "previewVideoUri": null,
                "thumbnailUrl": null,
                "contentUrl": null,
                "visionResult": {
                    "leftEye": {
                        "x": 0,
                        "y": 0,
                        "z": 0,
                        "xPercentage": 0,
                        "yPercentage": 0
                    },
                    "rightEye": {
                        "x": 0,
                        "y": 0,
                        "z": 0,
                        "xPercentage": 0,
                        "yPercentage": 0
                    }
                },
                "width": 1920,
                "height": 1080,
                "length": null
            },
            {
                "id": 756659,
                "type": "photo",
                "isCover": false,
                "isNoticeCover": false,
                "isPreorderCover": false,
                "isCompleted": true,
                "isPreview": false,
                "previewVideoUri": null,
                "thumbnailUrl": null,
                "contentUrl": null,
                "visionResult": {
                    "leftEye": {
                        "x": 0,
                        "y": 0,
                        "z": 0,
                        "xPercentage": 0,
                        "yPercentage": 0
                    },
                    "rightEye": {
                        "x": 0,
                        "y": 0,
                        "z": 0,
                        "xPercentage": 0,
                        "yPercentage": 0
                    }
                },
                "width": 1920,
                "height": 1080,
                "length": null
            },
            {
                "id": 756660,
                "type": "photo",
                "isCover": false,
                "isNoticeCover": false,
                "isPreorderCover": false,
                "isCompleted": true,
                "isPreview": false,
                "previewVideoUri": null,
                "thumbnailUrl": null,
                "contentUrl": null,
                "visionResult": {
                    "leftEye": {
                        "x": 0,
                        "y": 0,
                        "z": 0,
                        "xPercentage": 0,
                        "yPercentage": 0
                    },
                    "rightEye": {
                        "x": 0,
                        "y": 0,
                        "z": 0,
                        "xPercentage": 0,
                        "yPercentage": 0
                    }
                },
                "width": 1920,
                "height": 1080,
                "length": null
            },
            {
                "id": 756651,
                "type": "photo",
                "isCover": false,
                "isNoticeCover": false,
                "isPreorderCover": false,
                "isCompleted": true,
                "isPreview": false,
                "previewVideoUri": null,
                "thumbnailUrl": null,
                "contentUrl": null,
                "visionResult": {
                    "leftEye": {
                        "x": 0,
                        "y": 0,
                        "z": 0,
                        "xPercentage": 0,
                        "yPercentage": 0
                    },
                    "rightEye": {
                        "x": 0,
                        "y": 0,
                        "z": 0,
                        "xPercentage": 0,
                        "yPercentage": 0
                    }
                },
                "width": 1920,
                "height": 1080,
                "length": null
            },
            {
                "id": 756655,
                "type": "photo",
                "isCover": false,
                "isNoticeCover": false,
                "isPreorderCover": false,
                "isCompleted": true,
                "isPreview": false,
                "previewVideoUri": null,
                "thumbnailUrl": null,
                "contentUrl": null,
                "visionResult": {
                    "leftEye": {
                        "x": 0,
                        "y": 0,
                        "z": 0,
                        "xPercentage": 0,
                        "yPercentage": 0
                    },
                    "rightEye": {
                        "x": 0,
                        "y": 0,
                        "z": 0,
                        "xPercentage": 0,
                        "yPercentage": 0
                    }
                },
                "width": 1920,
                "height": 1080,
                "length": null
            },
            {
                "id": 756641,
                "type": "photo",
                "isCover": false,
                "isNoticeCover": false,
                "isPreorderCover": false,
                "isCompleted": true,
                "isPreview": false,
                "previewVideoUri": null,
                "thumbnailUrl": null,
                "contentUrl": null,
                "visionResult": {
                    "leftEye": {
                        "x": 0,
                        "y": 0,
                        "z": 0,
                        "xPercentage": 0,
                        "yPercentage": 0
                    },
                    "rightEye": {
                        "x": 0,
                        "y": 0,
                        "z": 0,
                        "xPercentage": 0,
                        "yPercentage": 0
                    }
                },
                "width": 1920,
                "height": 1080,
                "length": null
            },
            {
                "id": 756642,
                "type": "photo",
                "isCover": false,
                "isNoticeCover": false,
                "isPreorderCover": false,
                "isCompleted": true,
                "isPreview": false,
                "previewVideoUri": null,
                "thumbnailUrl": null,
                "contentUrl": null,
                "visionResult": {
                    "leftEye": {
                        "x": 0,
                        "y": 0,
                        "z": 0,
                        "xPercentage": 0,
                        "yPercentage": 0
                    },
                    "rightEye": {
                        "x": 0,
                        "y": 0,
                        "z": 0,
                        "xPercentage": 0,
                        "yPercentage": 0
                    }
                },
                "width": 1920,
                "height": 1080,
                "length": null
            },
            {
                "id": 756652,
                "type": "photo",
                "isCover": false,
                "isNoticeCover": false,
                "isPreorderCover": false,
                "isCompleted": true,
                "isPreview": false,
                "previewVideoUri": null,
                "thumbnailUrl": null,
                "contentUrl": null,
                "visionResult": {
                    "leftEye": {
                        "x": 0,
                        "y": 0,
                        "z": 0,
                        "xPercentage": 0,
                        "yPercentage": 0
                    },
                    "rightEye": {
                        "x": 0,
                        "y": 0,
                        "z": 0,
                        "xPercentage": 0,
                        "yPercentage": 0
                    }
                },
                "width": 1920,
                "height": 1080,
                "length": null
            },
            {
                "id": 756644,
                "type": "photo",
                "isCover": false,
                "isNoticeCover": false,
                "isPreorderCover": false,
                "isCompleted": true,
                "isPreview": false,
                "previewVideoUri": null,
                "thumbnailUrl": null,
                "contentUrl": null,
                "visionResult": {
                    "leftEye": {
                        "x": 0,
                        "y": 0,
                        "z": 0,
                        "xPercentage": 0,
                        "yPercentage": 0
                    },
                    "rightEye": {
                        "x": 0,
                        "y": 0,
                        "z": 0,
                        "xPercentage": 0,
                        "yPercentage": 0
                    }
                },
                "width": 1920,
                "height": 1080,
                "length": null
            },
            {
                "id": 756656,
                "type": "photo",
                "isCover": false,
                "isNoticeCover": false,
                "isPreorderCover": false,
                "isCompleted": true,
                "isPreview": false,
                "previewVideoUri": null,
                "thumbnailUrl": null,
                "contentUrl": null,
                "visionResult": {
                    "leftEye": {
                        "x": 0,
                        "y": 0,
                        "z": 0,
                        "xPercentage": 0,
                        "yPercentage": 0
                    },
                    "rightEye": {
                        "x": 0,
                        "y": 0,
                        "z": 0,
                        "xPercentage": 0,
                        "yPercentage": 0
                    }
                },
                "width": 1920,
                "height": 1080,
                "length": null
            },
            {
                "id": 756657,
                "type": "photo",
                "isCover": false,
                "isNoticeCover": false,
                "isPreorderCover": false,
                "isCompleted": true,
                "isPreview": false,
                "previewVideoUri": null,
                "thumbnailUrl": null,
                "contentUrl": null,
                "visionResult": {
                    "leftEye": {
                        "x": 0,
                        "y": 0,
                        "z": 0,
                        "xPercentage": 0,
                        "yPercentage": 0
                    },
                    "rightEye": {
                        "x": 0,
                        "y": 0,
                        "z": 0,
                        "xPercentage": 0,
                        "yPercentage": 0
                    }
                },
                "width": 1920,
                "height": 1080,
                "length": null
            },
            {
                "id": 756643,
                "type": "photo",
                "isCover": false,
                "isNoticeCover": false,
                "isPreorderCover": false,
                "isCompleted": true,
                "isPreview": false,
                "previewVideoUri": null,
                "thumbnailUrl": null,
                "contentUrl": null,
                "visionResult": {
                    "leftEye": {
                        "x": 0,
                        "y": 0,
                        "z": 0,
                        "xPercentage": 0,
                        "yPercentage": 0
                    },
                    "rightEye": {
                        "x": 0,
                        "y": 0,
                        "z": 0,
                        "xPercentage": 0,
                        "yPercentage": 0
                    }
                },
                "width": 1920,
                "height": 1080,
                "length": null
            },
            {
                "id": 756636,
                "type": "photo",
                "isCover": false,
                "isNoticeCover": false,
                "isPreorderCover": false,
                "isCompleted": true,
                "isPreview": false,
                "previewVideoUri": null,
                "thumbnailUrl": null,
                "contentUrl": null,
                "visionResult": {
                    "leftEye": {
                        "x": 0,
                        "y": 0,
                        "z": 0,
                        "xPercentage": 0,
                        "yPercentage": 0
                    },
                    "rightEye": {
                        "x": 0,
                        "y": 0,
                        "z": 0,
                        "xPercentage": 0,
                        "yPercentage": 0
                    }
                },
                "width": 1920,
                "height": 1080,
                "length": null
            },
            {
                "id": 756646,
                "type": "photo",
                "isCover": false,
                "isNoticeCover": false,
                "isPreorderCover": false,
                "isCompleted": true,
                "isPreview": false,
                "previewVideoUri": null,
                "thumbnailUrl": null,
                "contentUrl": null,
                "visionResult": {
                    "leftEye": {
                        "x": 0,
                        "y": 0,
                        "z": 0,
                        "xPercentage": 0,
                        "yPercentage": 0
                    },
                    "rightEye": {
                        "x": 0,
                        "y": 0,
                        "z": 0,
                        "xPercentage": 0,
                        "yPercentage": 0
                    }
                },
                "width": 1920,
                "height": 1080,
                "length": null
            },
            {
                "id": 756638,
                "type": "photo",
                "isCover": false,
                "isNoticeCover": false,
                "isPreorderCover": false,
                "isCompleted": true,
                "isPreview": false,
                "previewVideoUri": null,
                "thumbnailUrl": null,
                "contentUrl": null,
                "visionResult": {
                    "leftEye": {
                        "x": 0,
                        "y": 0,
                        "z": 0,
                        "xPercentage": 0,
                        "yPercentage": 0
                    },
                    "rightEye": {
                        "x": 0,
                        "y": 0,
                        "z": 0,
                        "xPercentage": 0,
                        "yPercentage": 0
                    }
                },
                "width": 1920,
                "height": 1080,
                "length": null
            },
            {
                "id": 756639,
                "type": "photo",
                "isCover": false,
                "isNoticeCover": false,
                "isPreorderCover": false,
                "isCompleted": true,
                "isPreview": false,
                "previewVideoUri": null,
                "thumbnailUrl": null,
                "contentUrl": null,
                "visionResult": {
                    "leftEye": {
                        "x": 0,
                        "y": 0,
                        "z": 0,
                        "xPercentage": 0,
                        "yPercentage": 0
                    },
                    "rightEye": {
                        "x": 0,
                        "y": 0,
                        "z": 0,
                        "xPercentage": 0,
                        "yPercentage": 0
                    }
                },
                "width": 1920,
                "height": 1080,
                "length": null
            },
            {
                "id": 756635,
                "type": "photo",
                "isCover": false,
                "isNoticeCover": false,
                "isPreorderCover": false,
                "isCompleted": true,
                "isPreview": false,
                "previewVideoUri": null,
                "thumbnailUrl": null,
                "contentUrl": null,
                "visionResult": {
                    "leftEye": {
                        "x": 0,
                        "y": 0,
                        "z": 0,
                        "xPercentage": 0,
                        "yPercentage": 0
                    },
                    "rightEye": {
                        "x": 0,
                        "y": 0,
                        "z": 0,
                        "xPercentage": 0,
                        "yPercentage": 0
                    }
                },
                "width": 1920,
                "height": 1080,
                "length": null
            },
            {
                "id": 756648,
                "type": "photo",
                "isCover": false,
                "isNoticeCover": false,
                "isPreorderCover": false,
                "isCompleted": true,
                "isPreview": false,
                "previewVideoUri": null,
                "thumbnailUrl": null,
                "contentUrl": null,
                "visionResult": {
                    "leftEye": {
                        "x": 0,
                        "y": 0,
                        "z": 0,
                        "xPercentage": 0,
                        "yPercentage": 0
                    },
                    "rightEye": {
                        "x": 0,
                        "y": 0,
                        "z": 0,
                        "xPercentage": 0,
                        "yPercentage": 0
                    }
                },
                "width": 1920,
                "height": 1080,
                "length": null
            },
            {
                "id": 756645,
                "type": "photo",
                "isCover": false,
                "isNoticeCover": false,
                "isPreorderCover": false,
                "isCompleted": true,
                "isPreview": false,
                "previewVideoUri": null,
                "thumbnailUrl": null,
                "contentUrl": null,
                "visionResult": {
                    "leftEye": {
                        "x": 0,
                        "y": 0,
                        "z": 0,
                        "xPercentage": 0,
                        "yPercentage": 0
                    },
                    "rightEye": {
                        "x": 0,
                        "y": 0,
                        "z": 0,
                        "xPercentage": 0,
                        "yPercentage": 0
                    }
                },
                "width": 1920,
                "height": 1080,
                "length": null
            },
            {
                "id": 756637,
                "type": "photo",
                "isCover": false,
                "isNoticeCover": false,
                "isPreorderCover": false,
                "isCompleted": true,
                "isPreview": false,
                "previewVideoUri": null,
                "thumbnailUrl": null,
                "contentUrl": null,
                "visionResult": {
                    "leftEye": {
                        "x": 0,
                        "y": 0,
                        "z": 0,
                        "xPercentage": 0,
                        "yPercentage": 0
                    },
                    "rightEye": {
                        "x": 0,
                        "y": 0,
                        "z": 0,
                        "xPercentage": 0,
                        "yPercentage": 0
                    }
                },
                "width": 1920,
                "height": 1080,
                "length": null
            },
            {
                "id": 756650,
                "type": "photo",
                "isCover": false,
                "isNoticeCover": false,
                "isPreorderCover": false,
                "isCompleted": true,
                "isPreview": false,
                "previewVideoUri": null,
                "thumbnailUrl": null,
                "contentUrl": null,
                "visionResult": {
                    "leftEye": {
                        "x": 0,
                        "y": 0,
                        "z": 0,
                        "xPercentage": 0,
                        "yPercentage": 0
                    },
                    "rightEye": {
                        "x": 0,
                        "y": 0,
                        "z": 0,
                        "xPercentage": 0,
                        "yPercentage": 0
                    }
                },
                "width": 1920,
                "height": 1080,
                "length": null
            },
            {
                "id": 756633,
                "type": "photo",
                "isCover": false,
                "isNoticeCover": false,
                "isPreorderCover": false,
                "isCompleted": true,
                "isPreview": false,
                "previewVideoUri": null,
                "thumbnailUrl": null,
                "contentUrl": null,
                "visionResult": {
                    "leftEye": {
                        "x": 0,
                        "y": 0,
                        "z": 0,
                        "xPercentage": 0,
                        "yPercentage": 0
                    },
                    "rightEye": {
                        "x": 0,
                        "y": 0,
                        "z": 0,
                        "xPercentage": 0,
                        "yPercentage": 0
                    }
                },
                "width": 1920,
                "height": 1080,
                "length": null
            },
            {
                "id": 756649,
                "type": "photo",
                "isCover": false,
                "isNoticeCover": false,
                "isPreorderCover": false,
                "isCompleted": true,
                "isPreview": false,
                "previewVideoUri": null,
                "thumbnailUrl": null,
                "contentUrl": null,
                "visionResult": {
                    "leftEye": {
                        "x": 0,
                        "y": 0,
                        "z": 0,
                        "xPercentage": 0,
                        "yPercentage": 0
                    },
                    "rightEye": {
                        "x": 0,
                        "y": 0,
                        "z": 0,
                        "xPercentage": 0,
                        "yPercentage": 0
                    }
                },
                "width": 1920,
                "height": 1080,
                "length": null
            },
            {
                "id": 756654,
                "type": "photo",
                "isCover": false,
                "isNoticeCover": false,
                "isPreorderCover": false,
                "isCompleted": true,
                "isPreview": false,
                "previewVideoUri": null,
                "thumbnailUrl": null,
                "contentUrl": null,
                "visionResult": {
                    "leftEye": {
                        "x": 0,
                        "y": 0,
                        "z": 0,
                        "xPercentage": 0,
                        "yPercentage": 0
                    },
                    "rightEye": {
                        "x": 0,
                        "y": 0,
                        "z": 0,
                        "xPercentage": 0,
                        "yPercentage": 0
                    }
                },
                "width": 1920,
                "height": 1080,
                "length": null
            },
            {
                "id": 756647,
                "type": "photo",
                "isCover": false,
                "isNoticeCover": false,
                "isPreorderCover": false,
                "isCompleted": true,
                "isPreview": false,
                "previewVideoUri": null,
                "thumbnailUrl": null,
                "contentUrl": null,
                "visionResult": {
                    "leftEye": {
                        "x": 0,
                        "y": 0,
                        "z": 0,
                        "xPercentage": 0,
                        "yPercentage": 0
                    },
                    "rightEye": {
                        "x": 0,
                        "y": 0,
                        "z": 0,
                        "xPercentage": 0,
                        "yPercentage": 0
                    }
                },
                "width": 1920,
                "height": 1080,
                "length": null
            },
            {
                "id": 15678,
                "type": "video",
                "isCover": false,
                "isNoticeCover": false,
                "isPreorderCover": false,
                "isCompleted": true,
                "isPreview": false,
                "previewVideoUri": null,
                "thumbnailUrl": null,
                "contentUrl": null,
                "visionResult": {
                    "leftEye": {
                        "x": 0,
                        "y": 0,
                        "z": 0,
                        "xPercentage": 0,
                        "yPercentage": 0
                    },
                    "rightEye": {
                        "x": 0,
                        "y": 0,
                        "z": 0,
                        "xPercentage": 0,
                        "yPercentage": 0
                    }
                },
                "width": 3840,
                "height": 2160,
                "length": "00:03:52"
            }
        ]
    },
    "header": {
        "translateStatus": "completed",
        "contractUrlList": [],
        "canViewAnalytics": false,
        "canExamine": false,
        "canViewContract": false
    },
    "canShowTag": false,
    "canShowLog": false,
    "canShowTransferFileStatus": false,
    "canChangeLayoutMode": false
}